{
  "yks": [
    {
      "Program Kodu": "111690721",
      "Üniversite": "İstanbul Üniversitesi-Cerrahpaşa",
      "Fakülte": "Spor Bilimleri Fakültesi",
      "Üniversite Türü": "Devlet",
      "Program Adı": "S",
      "Öğretim Türü": "Örgün",
      "Yıl": [
        "2025",
        "2024",
        "2023",
        "2022",
        "2021"
      ],
      "Kontenjan": [
        "44+2+0+0+044+2+0+0+044+2+0+2+044+2-"
      ],
      "Yerleşen": [
        "46",
        "44+2+0+0+0",
        "4846"
      ],
      "Taban Sıralama": [
        "332,040",
        "388,601",
        "384,934"
      ],
      "Taban Puan": [
        "302.699",
        "303.482",
        "303.872"
      ],
      "Şehir": "İstanbul",
      "Ücret": "Ücretsiz"
    },
    {
      "Program Kodu": "204790527",
      "Üniversite": "İstanbul Okan Üniversitesi",
      "Fakülte": "Uygulamalı Bilimler Fakültesi",
      "Üniversite Türü": "Vakıf",
      "Program Adı": "S",
      "Öğretim Türü": "Örgün",
      "Yıl": [
        "2025",
        "2024",
        "2023",
        "2022",
        "2021"
      ],
      "Kontenjan": [
        "4+0+1+0+14+0+1+0+1---"
      ],
      "Yerleşen": [
        "6",
        "4+0+1+0+1"
      ],
      "Taban Sıralama": [
        "404,803"
      ],
      "Taban Puan": [
        "292.262"
      ],
      "Şehir": "İstanbul",
      "Ücret": "Burslu"
    },
    {
      "Program Kodu": "111810932",
      "Üniversite": "Sakarya Uygulamalı Bilimler Üniversitesi",
      "Fakülte": "Spor Bilimleri Fakültesi",
      "Üniversite Türü": "Devlet",
      "Program Adı": "S",
      "Öğretim Türü": "Örgün",
      "Yıl": [
        "2025",
        "2024",
        "2023",
        "2022",
        "2021"
      ],
      "Kontenjan": [
        "50+2+0+2+050+2+0+2+050+2+0+2+050+250+2"
      ],
      "Yerleşen": [
        "54",
        "50+2+0+2+0",
        "535252"
      ],
      "Taban Sıralama": [
        "488,255",
        "593,457",
        "564,244",
        "568,987"
      ],
      "Taban Puan": [
        "281.986",
        "277.653",
        "279.772",
        "21.466"
      ],
      "Şehir": "Sakarya",
      "Ücret": "Ücretsiz"
    },
    {
      "Program Kodu": "106610525",
      "Üniversite": "Kırıkkale Üniversitesi",
      "Fakülte": "Spor Bilimleri Fakültesi",
      "Üniversite Türü": "Devlet",
      "Program Adı": "S",
      "Öğretim Türü": "Örgün",
      "Yıl": [
        "2025",
        "2024",
        "2023",
        "2022",
        "2021"
      ],
      "Kontenjan": [
        "50+2+0+2+050+2+0+2+050+2+0+2+050+250+2"
      ],
      "Yerleşen": [
        "53",
        "52+0+0+1+0",
        "535224"
      ],
      "Taban Sıralama": [
        "717,602",
        "758,838",
        "735,081"
      ],
      "Taban Puan": [
        "259.376",
        "261.117",
        "262.291"
      ],
      "Şehir": "Kırıkkale",
      "Ücret": "Ücretsiz"
    },
    {
      "Program Kodu": "109890113",
      "Üniversite": "Uşak Üniversitesi",
      "Fakülte": "Spor Bilimleri Fakültesi",
      "Üniversite Türü": "Devlet",
      "Program Adı": "S",
      "Öğretim Türü": "Örgün",
      "Yıl": [
        "2025",
        "2024",
        "2023",
        "2022",
        "2021"
      ],
      "Kontenjan": [
        "50+2+0+2+050+2+0+2+050+2+0+2+050+250+2"
      ],
      "Yerleşen": [
        "53",
        "52+0+0+1+0",
        "52529"
      ],
      "Taban Sıralama": [
        "719,924",
        "762,638",
        "755,718"
      ],
      "Taban Puan": [
        "259.176",
        "260.772",
        "260.405"
      ],
      "Şehir": "Uşak",
      "Ücret": "Ücretsiz"
    },
    {
      "Program Kodu": "105310804",
      "Üniversite": "İnönü Üniversitesi",
      "Fakülte": "Spor Bilimleri Fakültesi",
      "Üniversite Türü": "Devlet",
      "Program Adı": "S",
      "Öğretim Türü": "Örgün",
      "Yıl": [
        "2025",
        "2024",
        "2023",
        "2022",
        "2021"
      ],
      "Kontenjan": [
        "55+2+0+2+655+2+0+2+1450+2+0+2+1350+250+2"
      ],
      "Yerleşen": [
        "73",
        "57+0+0+2+14",
        "655252"
      ],
      "Taban Sıralama": [
        "750,493",
        "646,485",
        "588,616",
        "556,981"
      ],
      "Taban Puan": [
        "256.558",
        "272.026",
        "277.027",
        "225.175"
      ],
      "Şehir": "Malatya",
      "Ücret": "Ücretsiz"
    },
    {
      "Program Kodu": "107390124",
      "Üniversite": "Burdur Mehmet Akif Ersoy Üniversitesi",
      "Fakülte": "Spor Bilimleri Fakültesi",
      "Üniversite Türü": "Devlet",
      "Program Adı": "S",
      "Öğretim Türü": "Örgün",
      "Yıl": [
        "2025",
        "2024",
        "2023",
        "2022",
        "2021"
      ],
      "Kontenjan": [
        "50+2+0+2+050+2+0+2+050+2+0+2+050+250+2"
      ],
      "Yerleşen": [
        "53",
        "52+0+0+1+0",
        "525212"
      ],
      "Taban Sıralama": [
        "769,076",
        "810,023",
        "742,079"
      ],
      "Taban Puan": [
        "255.021",
        "256.517",
        "261.641"
      ],
      "Şehir": "Burdur",
      "Ücret": "Ücretsiz"
    },
    {
      "Program Kodu": "101690120",
      "Üniversite": "Bartın Üniversitesi",
      "Fakülte": "Spor Bilimleri Fakültesi",
      "Üniversite Türü": "Devlet",
      "Program Adı": "S",
      "Öğretim Türü": "Örgün",
      "Yıl": [
        "2025",
        "2024",
        "2023",
        "2022",
        "2021"
      ],
      "Kontenjan": [
        "50+2+0+2+050+2+0+2+050+2+0+2+050+250+2"
      ],
      "Yerleşen": [
        "53",
        "52+0+0+1+0",
        "53529"
      ],
      "Taban Sıralama": [
        "803,547",
        "819,393",
        "771,721"
      ],
      "Taban Puan": [
        "252.232",
        "55.688",
        "258.982"
      ],
      "Şehir": "Bartın",
      "Ücret": "Ücretsiz"
    },
    {
      "Program Kodu": "103910822",
      "Üniversite": "Fırat Üniversitesi",
      "Fakülte": "Spor Bilimleri Fakültesi",
      "Üniversite Türü": "Devlet",
      "Program Adı": "S",
      "Öğretim Türü": "Örgün",
      "Yıl": [
        "2025",
        "2024",
        "2023",
        "2022",
        "2021"
      ],
      "Kontenjan": [
        "55+2+0+0+655+2+0+0+1450+2+0+2+1350+250+2"
      ],
      "Yerleşen": [
        "71",
        "57+0+0+0+14",
        "675246"
      ],
      "Taban Sıralama": [
        "818,882",
        "677,682",
        "684,411"
      ],
      "Taban Puan": [
        "250.995",
        "268.862",
        "267.096"
      ],
      "Şehir": "Elazığ",
      "Ücret": "Ücretsiz"
    },
    {
      "Program Kodu": "108110321",
      "Üniversite": "Niğde Ömer Halisdemir Üniversitesi",
      "Fakülte": "Spor Bilimleri Fakültesi",
      "Üniversite Türü": "Devlet",
      "Program Adı": "S",
      "Öğretim Türü": "Örgün",
      "Yıl": [
        "2025",
        "2024",
        "2023",
        "2022",
        "2021"
      ],
      "Kontenjan": [
        "55+2+0+2+055+2+0+2+050+2+0+2+050+250+2"
      ],
      "Yerleşen": [
        "59",
        "57+0+0+2+0",
        "535221"
      ],
      "Taban Sıralama": [
        "870,672",
        "844,810",
        "801,490"
      ],
      "Taban Puan": [
        "246.959",
        "253.473",
        "256.365"
      ],
      "Şehir": "Niğde",
      "Ücret": "Ücretsiz"
    },
    {
      "Program Kodu": "106090164",
      "Üniversite": "Kahramanmaraş Sütçü İmam Üniversitesi",
      "Fakülte": "Spor Bilimleri Fakültesi",
      "Üniversite Türü": "Devlet",
      "Program Adı": "S",
      "Öğretim Türü": "Örgün",
      "Yıl": [
        "2025",
        "2024",
        "2023",
        "2022",
        "2021"
      ],
      "Kontenjan": [
        "45+2+0+2+545+2+0+2+1140+1+0+1+1040+140+1"
      ],
      "Yerleşen": [
        "60",
        "47+0+0+2+11",
        "524141"
      ],
      "Taban Sıralama": [
        "871,799",
        "778,655",
        "610,579",
        "574,519"
      ],
      "Taban Puan": [
        "246.869",
        "259.317",
        "274.652",
        "18.481"
      ],
      "Şehir": "Kahramanmaraş",
      "Ücret": "Ücretsiz"
    },
    {
      "Program Kodu": "106190236",
      "Üniversite": "Karabük Üniversitesi",
      "Fakülte": "Hasan Doğan Spor Bilimleri Fakültesi",
      "Üniversite Türü": "Devlet",
      "Program Adı": "S",
      "Öğretim Türü": "Örgün",
      "Yıl": [
        "2025",
        "2024",
        "2023",
        "2022",
        "2021"
      ],
      "Kontenjan": [
        "50+2+0+2+050+2+0+2+0---"
      ],
      "Yerleşen": [
        "54",
        "51+1+0+2+0"
      ],
      "Taban Sıralama": [
        "953,917"
      ],
      "Taban Puan": [
        "240.719"
      ],
      "Şehir": "Karabük",
      "Ücret": "Ücretsiz"
    },
    {
      "Program Kodu": "105290068",
      "Üniversite": "Iğdır Üniversitesi",
      "Fakülte": "Spor Bilimleri Fakültesi",
      "Üniversite Türü": "Devlet",
      "Program Adı": "S",
      "Öğretim Türü": "Örgün",
      "Yıl": [
        "2025",
        "2024",
        "2023",
        "2022",
        "2021"
      ],
      "Kontenjan": [
        "55+2+0+2+055+2+0+2+050+2+0+2+050+250+2"
      ],
      "Yerleşen": [
        "59",
        "57+0+0+2+0",
        "52527"
      ],
      "Taban Sıralama": [
        "1,143",
        "981,108",
        "995,849"
      ],
      "Taban Puan": [
        "227.244",
        "232.676",
        "240.777"
      ],
      "Şehir": "Iğdır",
      "Ücret": "Ücretsiz"
    },
    {
      "Program Kodu": "204790528",
      "Üniversite": "İstanbul Okan Üniversitesi",
      "Fakülte": "Uygulamalı Bilimler Fakültesi",
      "Üniversite Türü": "Vakıf",
      "Program Adı": "S",
      "Öğretim Türü": "Örgün",
      "Yıl": [
        "2025",
        "2024",
        "2023",
        "2022",
        "2021"
      ],
      "Kontenjan": [
        "25+0+0+0+025+0+0+0+0---"
      ],
      "Yerleşen": [
        "25",
        "25+0+0+0+0"
      ],
      "Taban Sıralama": [
        "1,265"
      ],
      "Taban Puan": [
        "218.711"
      ],
      "Şehir": "İstanbul",
      "Ücret": "%50 İndirimli"
    }
  ]
}