{
  "yks": [
    {
      "Program Kodu": "102710942",
      "Üniversite": "Çanakkale Onsekiz Mart Üniversitesi",
      "Fakülte": "Çanakkale Uygulamalı Bilimler Fakültesi",
      "Üniversite Türü": "Devlet",
      "Program Adı": "G",
      "Öğretim Türü": "Örgün",
      "Yıl": [
        "2025",
        "2024",
        "2023",
        "2022",
        "2021"
      ],
      "Kontenjan": [
        "35+1+0+1+035+1+0+1+030+1+0+1+030+130+1"
      ],
      "Yerleşen": [
        "37",
        "36+0+0+1+0",
        "32317"
      ],
      "Taban Sıralama": [
        "454,918",
        "483,764",
        "485,904"
      ],
      "Taban Puan": [
        "259.835",
        "267.643",
        "255.396"
      ],
      "Şehir": "Çanakkale",
      "Ücret": "Ücretsiz"
    },
    {
      "Program Kodu": "208450431",
      "Üniversite": "İstinye Üniversitesi",
      "Fakülte": "Meslek Yüksekokulu",
      "Üniversite Türü": "Vakıf",
      "Program Adı": "G",
      "Öğretim Türü": "Örgün",
      "Yıl": [
        "2025",
        "2024",
        "2023",
        "2022",
        "2021"
      ],
      "Kontenjan": [
        "4+0+1+0+14+0+1+0+14+0+1+0+1--"
      ],
      "Yerleşen": [
        "4+0+0+0+1",
        "4"
      ],
      "Taban Sıralama": [
        "639,329"
      ],
      "Taban Puan": [
        "321.51"
      ],
      "Şehir": "İstanbul",
      "Ücret": "Burslu"
    },
    {
      "Program Kodu": "206550524",
      "Üniversite": "Üsküdar Üniversitesi",
      "Fakülte": "Sağlık Hizmetleri Meslek Yüksekokulu",
      "Üniversite Türü": "Vakıf",
      "Program Adı": "G",
      "Öğretim Türü": "Örgün",
      "Yıl": [
        "2025",
        "2024",
        "2023",
        "2022",
        "2021"
      ],
      "Kontenjan": [
        "10+0+2+0+17+0+1+0+17+0+1+0+1--"
      ],
      "Yerleşen": [
        "7+0+0+0+0",
        "7"
      ],
      "Taban Sıralama": [
        "643,901"
      ],
      "Taban Puan": [
        "321.053"
      ],
      "Şehir": "İstanbul",
      "Ücret": "Burslu"
    },
    {
      "Program Kodu": "206050502",
      "Üniversite": "Yaşar Üniversitesi",
      "Fakülte": "Meslek Yüksekokulu",
      "Üniversite Türü": "Vakıf",
      "Program Adı": "G",
      "Öğretim Türü": "Örgün",
      "Yıl": [
        "2025",
        "2024",
        "2023",
        "2022",
        "2021"
      ],
      "Kontenjan": [
        "7+0+1+0+17+0+1+0+16+0+1+0+1--"
      ],
      "Yerleşen": [
        "7+0+0+0+0",
        "6"
      ],
      "Taban Sıralama": [
        "647,676"
      ],
      "Taban Puan": [
        "320.676"
      ],
      "Şehir": "İzmir",
      "Ücret": "Burslu"
    },
    {
      "Program Kodu": "111650024",
      "Üniversite": "İstanbul Üniversitesi-Cerrahpaşa",
      "Fakülte": "Veterinerlik Meslek Yüksekokulu",
      "Üniversite Türü": "Devlet",
      "Program Adı": "G",
      "Öğretim Türü": "Örgün",
      "Yıl": [
        "2025",
        "2024",
        "2023",
        "2022",
        "2021"
      ],
      "Kontenjan": [
        "30+1+0+0+050+2+0+0+050+2+0+2+0--"
      ],
      "Yerleşen": [
        "52+0+0+0+0",
        "Doldu-54"
      ],
      "Taban Sıralama": [
        "657,864",
        "682,917"
      ],
      "Taban Puan": [
        "319.662",
        "318.272"
      ],
      "Şehir": "İstanbul",
      "Ücret": "Ücretsiz"
    },
    {
      "Program Kodu": "103450226",
      "Üniversite": "Ege Üniversitesi",
      "Fakülte": "Ege Meslek Yüksekokulu",
      "Üniversite Türü": "Devlet",
      "Program Adı": "G",
      "Öğretim Türü": "Örgün",
      "Yıl": [
        "2025",
        "2024",
        "2023",
        "2022",
        "2021"
      ],
      "Kontenjan": [
        "35+1+0+0+060+2+0+0+060+2+0+2+0--"
      ],
      "Yerleşen": [
        "60+2+0+0+0",
        "Doldu-64"
      ],
      "Taban Sıralama": [
        "692,307",
        "705,294"
      ],
      "Taban Puan": [
        "316.326",
        "316.04"
      ],
      "Şehir": "İzmir",
      "Ücret": "Ücretsiz"
    },
    {
      "Program Kodu": "202450246",
      "Üniversite": "İstanbul Aydın Üniversitesi",
      "Fakülte": "Anadolu Bil Meslek Yüksekokulu",
      "Üniversite Türü": "Vakıf",
      "Program Adı": "G",
      "Öğretim Türü": "Örgün",
      "Yıl": [
        "2025",
        "2024",
        "2023",
        "2022",
        "2021"
      ],
      "Kontenjan": [
        "10+0+2+0+110+0+2+0+111+0+2+0+1--"
      ],
      "Yerleşen": [
        "10+0+1+0+1",
        "12"
      ],
      "Taban Sıralama": [
        "718,594"
      ],
      "Taban Puan": [
        "313.893"
      ],
      "Şehir": "İstanbul",
      "Ücret": "Burslu"
    },
    {
      "Program Kodu": "202753625",
      "Üniversite": "İstanbul Gelişim Üniversitesi",
      "Fakülte": "İstanbul Gelişim Meslek Yüksekokulu",
      "Üniversite Türü": "Vakıf",
      "Program Adı": "G",
      "Öğretim Türü": "Örgün",
      "Yıl": [
        "2025",
        "2024",
        "2023",
        "2022",
        "2021"
      ],
      "Kontenjan": [
        "4+0+1+0+14+0+1+0+18+0+1+0+1--"
      ],
      "Yerleşen": [
        "4+0+0+0+0",
        "Doldu-9"
      ],
      "Taban Sıralama": [
        "725,551",
        "870,572"
      ],
      "Taban Puan": [
        "313.247",
        "301.009"
      ],
      "Şehir": "İstanbul",
      "Ücret": "Burslu"
    },
    {
      "Program Kodu": "200690426",
      "Üniversite": "Başkent Üniversitesi",
      "Fakülte": "Kahramankazan Meslek Yüksekokulu",
      "Üniversite Türü": "Vakıf",
      "Program Adı": "G",
      "Öğretim Türü": "Örgün",
      "Yıl": [
        "2025",
        "2024",
        "2023",
        "2022",
        "2021"
      ],
      "Kontenjan": [
        "6+0+0+0+15+0+0+0+16+0+0+0+1--"
      ],
      "Yerleşen": [
        "5+0+0+0+1",
        "6"
      ],
      "Taban Sıralama": [
        "832,882"
      ],
      "Taban Puan": [
        "303.98"
      ],
      "Şehir": "Ankara",
      "Ücret": "Burslu"
    },
    {
      "Program Kodu": "109750223",
      "Üniversite": "Bursa Uludağ Üniversitesi",
      "Fakülte": "Teknik Bilimler Meslek Yüksekokulu",
      "Üniversite Türü": "Devlet",
      "Program Adı": "G",
      "Öğretim Türü": "Örgün",
      "Yıl": [
        "2025",
        "2024",
        "2023",
        "2022",
        "2021"
      ],
      "Kontenjan": [
        "35+1+0+0+080+2+0+0+080+2+0+2+0--"
      ],
      "Yerleşen": [
        "82+0+0+0+0",
        "Doldu-84"
      ],
      "Taban Sıralama": [
        "833,785",
        "934,493"
      ],
      "Taban Puan": [
        "303.906",
        "295.756"
      ],
      "Şehir": "Bursa",
      "Ücret": "Ücretsiz"
    },
    {
      "Program Kodu": "207590506",
      "Üniversite": "İstanbul Esenyurt Üniversitesi",
      "Fakülte": "Meslek Yüksekokulu",
      "Üniversite Türü": "Vakıf",
      "Program Adı": "G",
      "Öğretim Türü": "Örgün",
      "Yıl": [
        "2025",
        "2024",
        "2023",
        "2022",
        "2021"
      ],
      "Kontenjan": [
        "5+0+0+0+14+0+1+0+1---"
      ],
      "Yerleşen": [
        "4+0+0+0+1"
      ],
      "Taban Sıralama": [
        "862,234"
      ],
      "Taban Puan": [
        "301.595"
      ],
      "Şehir": "İstanbul",
      "Ücret": "Burslu"
    },
    {
      "Program Kodu": "110090158",
      "Üniversite": "Ankara Yıldırım Beyazıt Üniversitesi",
      "Fakülte": "Sağlık Hizmetleri Meslek Yüksekokulu",
      "Üniversite Türü": "Devlet",
      "Program Adı": "G",
      "Öğretim Türü": "Örgün",
      "Yıl": [
        "2025",
        "2024",
        "2023",
        "2022",
        "2021"
      ],
      "Kontenjan": [
        "35+1+0+1+050+2+0+2+050+2+0+2+0--"
      ],
      "Yerleşen": [
        "52+0+0+2+0",
        "Doldu-54"
      ],
      "Taban Sıralama": [
        "870,136",
        "970,130"
      ],
      "Taban Puan": [
        "300.987",
        "292.921"
      ],
      "Şehir": "Ankara",
      "Ücret": "Ücretsiz"
    },
    {
      "Program Kodu": "108570527",
      "Üniversite": "Osmaniye Korkut Ata Üniversitesi",
      "Fakülte": "Kadirli Uygulamalı Bilimler Fakültesi",
      "Üniversite Türü": "Devlet",
      "Program Adı": "G",
      "Öğretim Türü": "Örgün",
      "Yıl": [
        "2025",
        "2024",
        "2023",
        "2022",
        "2021"
      ],
      "Kontenjan": [
        "45+2+0+2+545+2+0+2+1140+1+0+1+1030+130+1"
      ],
      "Yerleşen": [
        "60",
        "47+0+0+2+11",
        "5231"
      ],
      "Taban Sıralama": [
        "898,535",
        "947,330",
        "1,087"
      ],
      "Taban Puan": [
        "218.147",
        "218.943",
        "198.475"
      ],
      "Şehir": "Osmaniye",
      "Ücret": "Ücretsiz"
    },
    {
      "Program Kodu": "103190563",
      "Üniversite": "Dokuz Eylül Üniversitesi",
      "Fakülte": "Efes Meslek Yüksekokulu (Selçuk)",
      "Üniversite Türü": "Devlet",
      "Program Adı": "G",
      "Öğretim Türü": "Örgün",
      "Yıl": [
        "2025",
        "2024",
        "2023",
        "2022",
        "2021"
      ],
      "Kontenjan": [
        "35+1+0+0+040+1+0+0+040+1+0+1+0--"
      ],
      "Yerleşen": [
        "41+0+0+0+0",
        "Doldu-42"
      ],
      "Taban Sıralama": [
        "971,078",
        "1,025"
      ],
      "Taban Puan": [
        "293.329",
        "288.663"
      ],
      "Şehir": "İzmir",
      "Ücret": "Ücretsiz"
    },
    {
      "Program Kodu": "104510259",
      "Üniversite": "Giresun Üniversitesi",
      "Fakülte": "Şebinkarahisar Uygulamalı Bilimler Yüksekokulu",
      "Üniversite Türü": "Devlet",
      "Program Adı": "G",
      "Öğretim Türü": "Örgün",
      "Yıl": [
        "2025",
        "2024",
        "2023",
        "2022",
        "2021"
      ],
      "Kontenjan": [
        "55+2+0+2+055+2+0+2+050+2+0+2+045+245+2"
      ],
      "Yerleşen": [
        "59",
        "57+0+0+2+0",
        "5447"
      ],
      "Taban Sıralama": [
        "980,758",
        "1,018",
        "721,368"
      ],
      "Taban Puan": [
        "211.616",
        "213.395",
        "174.913"
      ],
      "Şehir": "Giresun",
      "Ücret": "Ücretsiz"
    },
    {
      "Program Kodu": "100790420",
      "Üniversite": "Akdeniz Üniversitesi",
      "Fakülte": "Manavgat Meslek Yüksekokulu",
      "Üniversite Türü": "Devlet",
      "Program Adı": "G",
      "Öğretim Türü": "Örgün",
      "Yıl": [
        "2025",
        "2024",
        "2023",
        "2022",
        "2021"
      ],
      "Kontenjan": [
        "35+1+0+1+040+1+0+1+040+1+0+1+0--"
      ],
      "Yerleşen": [
        "40+1+0+1+0",
        "Doldu-42"
      ],
      "Taban Sıralama": [
        "1,035",
        "581,178"
      ],
      "Taban Puan": [
        "288.708",
        "277.634"
      ],
      "Şehir": "Antalya",
      "Ücret": "Ücretsiz"
    },
    {
      "Program Kodu": "106950812",
      "Üniversite": "Kocaeli Üniversitesi",
      "Fakülte": "İzmit Meslek Yüksekokulu",
      "Üniversite Türü": "Devlet",
      "Program Adı": "G",
      "Öğretim Türü": "Örgün",
      "Yıl": [
        "2025",
        "2024",
        "2023",
        "2022",
        "2021"
      ],
      "Kontenjan": [
        "35+1+0+1+055+2+0+2+055+2+0+2+0--"
      ],
      "Yerleşen": [
        "57+0+0+2+0",
        "Doldu-59"
      ],
      "Taban Sıralama": [
        "1,066",
        "041,169"
      ],
      "Taban Puan": [
        "286.559",
        "278.221"
      ],
      "Şehir": "Kocaeli",
      "Ücret": "Ücretsiz"
    },
    {
      "Program Kodu": "101150129",
      "Üniversite": "Ankara Üniversitesi",
      "Fakülte": "Kalecik Meslek Yüksekokulu",
      "Üniversite Türü": "Devlet",
      "Program Adı": "G",
      "Öğretim Türü": "Örgün",
      "Yıl": [
        "2025",
        "2024",
        "2023",
        "2022",
        "2021"
      ],
      "Kontenjan": [
        "35+1+0+0+050+2+0+0+050+2+0+2+0--"
      ],
      "Yerleşen": [
        "52+0+0+0+0",
        "Doldu-54"
      ],
      "Taban Sıralama": [
        "1,113",
        "271,327"
      ],
      "Taban Puan": [
        "283.325",
        "267.568"
      ],
      "Şehir": "Ankara",
      "Ücret": "Ücretsiz"
    },
    {
      "Program Kodu": "107450832",
      "Üniversite": "Mersin Üniversitesi",
      "Fakülte": "Teknik Bilimler Meslek Yüksekokulu",
      "Üniversite Türü": "Devlet",
      "Program Adı": "G",
      "Öğretim Türü": "Örgün",
      "Yıl": [
        "2025",
        "2024",
        "2023",
        "2022",
        "2021"
      ],
      "Kontenjan": [
        "35+1+0+1+050+2+0+2+050+2+0+2+0--"
      ],
      "Yerleşen": [
        "52+0+0+2+0",
        "Doldu-54"
      ],
      "Taban Sıralama": [
        "1,110",
        "031,211"
      ],
      "Taban Puan": [
        "283.516",
        "275.278"
      ],
      "Şehir": "Mersin",
      "Ücret": "Ücretsiz"
    },
    {
      "Program Kodu": "103450765",
      "Üniversite": "Ege Üniversitesi",
      "Fakülte": "Tire Kutsan Meslek Yüksekokulu",
      "Üniversite Türü": "Devlet",
      "Program Adı": "G",
      "Öğretim Türü": "Örgün",
      "Yıl": [
        "2025",
        "2024",
        "2023",
        "2022",
        "2021"
      ],
      "Kontenjan": [
        "35+1+0+0+055+2+0+0+055+2+0+2+0--"
      ],
      "Yerleşen": [
        "55+2+0+0+0",
        "Doldu-59"
      ],
      "Taban Sıralama": [
        "1,125",
        "231,196"
      ],
      "Taban Puan": [
        "282.485",
        "276.332"
      ],
      "Şehir": "İzmir",
      "Ücret": "Ücretsiz"
    },
    {
      "Program Kodu": "109750417",
      "Üniversite": "Bursa Uludağ Üniversitesi",
      "Fakülte": "Gemlik Asım Kocabıyık Meslek Yüksekokulu",
      "Üniversite Türü": "Devlet",
      "Program Adı": "G",
      "Öğretim Türü": "Örgün",
      "Yıl": [
        "2025",
        "2024",
        "2023",
        "2022",
        "2021"
      ],
      "Kontenjan": [
        "30+1+0+0+055+2+0+0+055+2+0+2+0--"
      ],
      "Yerleşen": [
        "57+0+0+0+0",
        "Doldu-59"
      ],
      "Taban Sıralama": [
        "1,128",
        "151,304"
      ],
      "Taban Puan": [
        "282.292",
        "69.075"
      ],
      "Şehir": "Bursa",
      "Ücret": "Ücretsiz"
    },
    {
      "Program Kodu": "110650043",
      "Üniversite": "Bandırma Onyedi Eylül Üniversitesi",
      "Fakülte": "Bandırma Meslek Yüksekokulu",
      "Üniversite Türü": "Devlet",
      "Program Adı": "G",
      "Öğretim Türü": "Örgün",
      "Yıl": [
        "2025",
        "2024",
        "2023",
        "2022",
        "2021"
      ],
      "Kontenjan": [
        "30+1+0+1+050+2+0+2+050+2+0+2+0--"
      ],
      "Yerleşen": [
        "52+0+0+2+0",
        "Doldu-54"
      ],
      "Taban Sıralama": [
        "1,174",
        "171,282"
      ],
      "Taban Puan": [
        "279.218",
        "270.546"
      ],
      "Şehir": "Balıkesir",
      "Ücret": "Ücretsiz"
    },
    {
      "Program Kodu": "102550352",
      "Üniversite": "Manisa Celâl Bayar Üniversitesi",
      "Fakülte": "Saruhanlı Meslek Yüksekokulu",
      "Üniversite Türü": "Devlet",
      "Program Adı": "G",
      "Öğretim Türü": "Örgün",
      "Yıl": [
        "2025",
        "2024",
        "2023",
        "2022",
        "2021"
      ],
      "Kontenjan": [
        "35+1+0+1+040+1+0+1+040+1+0+1+0--"
      ],
      "Yerleşen": [
        "41+0+0+1+0",
        "Doldu-42"
      ],
      "Taban Sıralama": [
        "1,188",
        "311,387"
      ],
      "Taban Puan": [
        "278.316",
        "263.745"
      ],
      "Şehir": "Manisa",
      "Ücret": "Ücretsiz"
    },
    {
      "Program Kodu": "111350463",
      "Üniversite": "Konya Teknik Üniversitesi",
      "Fakülte": "Teknik Bilimler Meslek Yüksekokulu",
      "Üniversite Türü": "Devlet",
      "Program Adı": "G",
      "Öğretim Türü": "Örgün",
      "Yıl": [
        "2025",
        "2024",
        "2023",
        "2022",
        "2021"
      ],
      "Kontenjan": [
        "35+1+0+1+050+2+0+2+050+2+0+2+0--"
      ],
      "Yerleşen": [
        "52+0+0+2+0",
        "Doldu-54"
      ],
      "Taban Sıralama": [
        "1,192",
        "011,339"
      ],
      "Taban Puan": [
        "278.036",
        "266.837"
      ],
      "Şehir": "Konya",
      "Ücret": "Ücretsiz"
    },
    {
      "Program Kodu": "100190243",
      "Üniversite": "Bolu Abant İzzet Baysal Üniversitesi",
      "Fakülte": "Bolu Teknik Bilimler Meslek Yüksekokulu",
      "Üniversite Türü": "Devlet",
      "Program Adı": "G",
      "Öğretim Türü": "Örgün",
      "Yıl": [
        "2025",
        "2024",
        "2023",
        "2022",
        "2021"
      ],
      "Kontenjan": [
        "30+1+0+1+030+1+0+1+0---"
      ],
      "Yerleşen": [
        "31+0+0+1+0"
      ],
      "Taban Sıralama": [
        "1,268"
      ],
      "Taban Puan": [
        "273.153"
      ],
      "Şehir": "Bolu",
      "Ücret": "Ücretsiz"
    },
    {
      "Program Kodu": "112350428",
      "Üniversite": "Kayseri Üniversitesi",
      "Fakülte": "Safiye Çıkrıkçıoğlu Meslek Yüksekokulu",
      "Üniversite Türü": "Devlet",
      "Program Adı": "G",
      "Öğretim Türü": "Örgün",
      "Yıl": [
        "2025",
        "2024",
        "2023",
        "2022",
        "2021"
      ],
      "Kontenjan": [
        "35+1+0+1+050+2+0+2+050+2+0+2+0--"
      ],
      "Yerleşen": [
        "52+0+0+2+0",
        "Doldu-54"
      ],
      "Taban Sıralama": [
        "1,286",
        "371,438"
      ],
      "Taban Puan": [
        "272.019",
        "260.524"
      ],
      "Şehir": "Kayseri",
      "Ücret": "Ücretsiz"
    },
    {
      "Program Kodu": "111850773",
      "Üniversite": "Sakarya Uygulamalı Bilimler Üniversitesi",
      "Fakülte": "Pamukova Meslek Yüksekokulu",
      "Üniversite Türü": "Devlet",
      "Program Adı": "G",
      "Öğretim Türü": "Örgün",
      "Yıl": [
        "2025",
        "2024",
        "2023",
        "2022",
        "2021"
      ],
      "Kontenjan": [
        "35+1+0+1+040+1+0+1+040+1+0+1+0--"
      ],
      "Yerleşen": [
        "41+0+0+1+0",
        "Doldu-42"
      ],
      "Taban Sıralama": [
        "1,294",
        "671,390"
      ],
      "Taban Puan": [
        "271.533",
        "263.529"
      ],
      "Şehir": "Sakarya",
      "Ücret": "Ücretsiz"
    },
    {
      "Program Kodu": "107950078",
      "Üniversite": "Tekirdağ Namık Kemal Üniversitesi",
      "Fakülte": "Teknik Bilimler Meslek Yüksekokulu",
      "Üniversite Türü": "Devlet",
      "Program Adı": "G",
      "Öğretim Türü": "Örgün",
      "Yıl": [
        "2025",
        "2024",
        "2023",
        "2022",
        "2021"
      ],
      "Kontenjan": [
        "35+1+0+1+080+2+0+2+080+2+0+2+0--"
      ],
      "Yerleşen": [
        "82+0+0+2+0",
        "Doldu-84"
      ],
      "Taban Sıralama": [
        "1,304",
        "561,455"
      ],
      "Taban Puan": [
        "270.847",
        "259.529"
      ],
      "Şehir": "Tekirdağ",
      "Ücret": "Ücretsiz"
    },
    {
      "Program Kodu": "100450077",
      "Üniversite": "Afyon Kocatepe Üniversitesi",
      "Fakülte": "Afyon Meslek Yüksekokulu",
      "Üniversite Türü": "Devlet",
      "Program Adı": "G",
      "Öğretim Türü": "Örgün",
      "Yıl": [
        "2025",
        "2024",
        "2023",
        "2022",
        "2021"
      ],
      "Kontenjan": [
        "35+1+0+1+050+2+0+2+050+2+0+2+0--"
      ],
      "Yerleşen": [
        "52+0+0+2+0",
        "Doldu-54"
      ],
      "Taban Sıralama": [
        "1,303",
        "361,477"
      ],
      "Taban Puan": [
        "270.943",
        "258.153"
      ],
      "Şehir": "Afyonkarahisar",
      "Ücret": "Ücretsiz"
    },
    {
      "Program Kodu": "109450314",
      "Üniversite": "Trakya Üniversitesi",
      "Fakülte": "Arda Meslek Yüksekokulu",
      "Üniversite Türü": "Devlet",
      "Program Adı": "G",
      "Öğretim Türü": "Örgün",
      "Yıl": [
        "2025",
        "2024",
        "2023",
        "2022",
        "2021"
      ],
      "Kontenjan": [
        "30+1+0+1+050+2+0+2+050+2+0+2+0--"
      ],
      "Yerleşen": [
        "52+0+0+2+0",
        "52"
      ],
      "Taban Sıralama": [
        "1,317"
      ],
      "Taban Puan": [
        "270.088"
      ],
      "Şehir": "Edirne",
      "Ücret": "Ücretsiz"
    },
    {
      "Program Kodu": "108251308",
      "Üniversite": "Ondokuz Mayıs Üniversitesi",
      "Fakülte": "Yeşilyurt Demir Çelik Meslek Yüksekokulu",
      "Üniversite Türü": "Devlet",
      "Program Adı": "G",
      "Öğretim Türü": "Örgün",
      "Yıl": [
        "2025",
        "2024",
        "2023",
        "2022",
        "2021"
      ],
      "Kontenjan": [
        "35+1+0+1+040+1+0+1+040+1+0+1+0--"
      ],
      "Yerleşen": [
        "41+0+0+1+0",
        "41"
      ],
      "Taban Sıralama": [
        "1,324"
      ],
      "Taban Puan": [
        "269.613"
      ],
      "Şehir": "Samsun",
      "Ücret": "Ücretsiz"
    },
    {
      "Program Kodu": "102751012",
      "Üniversite": "Çanakkale Onsekiz Mart Üniversitesi",
      "Fakülte": "Biga Meslek Yüksekokulu",
      "Üniversite Türü": "Devlet",
      "Program Adı": "G",
      "Öğretim Türü": "Örgün",
      "Yıl": [
        "2025",
        "2024",
        "2023",
        "2022",
        "2021"
      ],
      "Kontenjan": [
        "35+1+0+1+055+2+0+2+055+2+0+2+0--"
      ],
      "Yerleşen": [
        "57+0+0+2+0",
        "Doldu-59"
      ],
      "Taban Sıralama": [
        "1,320",
        "971,472"
      ],
      "Taban Puan": [
        "269.875",
        "258.432"
      ],
      "Şehir": "Çanakkale",
      "Ücret": "Ücretsiz"
    },
    {
      "Program Kodu": "109750586",
      "Üniversite": "Bursa Uludağ Üniversitesi",
      "Fakülte": "Karacabey Meslek Yüksekokulu",
      "Üniversite Türü": "Devlet",
      "Program Adı": "G",
      "Öğretim Türü": "Örgün",
      "Yıl": [
        "2025",
        "2024",
        "2023",
        "2022",
        "2021"
      ],
      "Kontenjan": [
        "30+1+0+0+050+2+0+0+050+2+0+2+0--"
      ],
      "Yerleşen": [
        "52+0+0+0+0",
        "53"
      ],
      "Taban Sıralama": [
        "1,350"
      ],
      "Taban Puan": [
        "268.02"
      ],
      "Şehir": "Bursa",
      "Ücret": "Ücretsiz"
    },
    {
      "Program Kodu": "109750532",
      "Üniversite": "Bursa Uludağ Üniversitesi",
      "Fakülte": "İznik Meslek Yüksekokulu",
      "Üniversite Türü": "Devlet",
      "Program Adı": "G",
      "Öğretim Türü": "Örgün",
      "Yıl": [
        "2025",
        "2024",
        "2023",
        "2022",
        "2021"
      ],
      "Kontenjan": [
        "30+1+0+0+050+2+0+0+050+2+0+2+0--"
      ],
      "Yerleşen": [
        "52+0+0+0+0",
        "Doldu-54"
      ],
      "Taban Sıralama": [
        "1,425",
        "731,603"
      ],
      "Taban Puan": [
        "263.416",
        "250.633"
      ],
      "Şehir": "Bursa",
      "Ücret": "Ücretsiz"
    },
    {
      "Program Kodu": "103050433",
      "Üniversite": "Dicle Üniversitesi",
      "Fakülte": "Diyarbakır Tarım Meslek Yüksekokulu",
      "Üniversite Türü": "Devlet",
      "Program Adı": "G",
      "Öğretim Türü": "Örgün",
      "Yıl": [
        "2025",
        "2024",
        "2023",
        "2022",
        "2021"
      ],
      "Kontenjan": [
        "35+1+0+1+450+2+0+2+1350+2+0+2+13--"
      ],
      "Yerleşen": [
        "52+0+0+2+13",
        "Doldu-67"
      ],
      "Taban Sıralama": [
        "1,416",
        "931,350"
      ],
      "Taban Puan": [
        "263.962",
        "266.13"
      ],
      "Şehir": "Diyarbakır",
      "Ücret": "Ücretsiz"
    },
    {
      "Program Kodu": "107950493",
      "Üniversite": "Tekirdağ Namık Kemal Üniversitesi",
      "Fakülte": "Çorlu Meslek Yüksekokulu",
      "Üniversite Türü": "Devlet",
      "Program Adı": "G",
      "Öğretim Türü": "Örgün",
      "Yıl": [
        "2025",
        "2024",
        "2023",
        "2022",
        "2021"
      ],
      "Kontenjan": [
        "35+1+0+1+040+1+0+1+040+1+0+1+0--"
      ],
      "Yerleşen": [
        "41+0+0+1+0",
        "Doldu-42"
      ],
      "Taban Sıralama": [
        "1,439",
        "261,568"
      ],
      "Taban Puan": [
        "262.563",
        "252.721"
      ],
      "Şehir": "Tekirdağ",
      "Ücret": "Ücretsiz"
    },
    {
      "Program Kodu": "103350642",
      "Üniversite": "Düzce Üniversitesi",
      "Fakülte": "Akçakoca Meslek Yüksekokulu",
      "Üniversite Türü": "Devlet",
      "Program Adı": "G",
      "Öğretim Türü": "Örgün",
      "Yıl": [
        "2025",
        "2024",
        "2023",
        "2022",
        "2021"
      ],
      "Kontenjan": [
        "35+1+0+1+045+2+0+2+045+2+0+2+0--"
      ],
      "Yerleşen": [
        "47+0+0+2+0",
        "Doldu-49"
      ],
      "Taban Sıralama": [
        "1,458",
        "081,668"
      ],
      "Taban Puan": [
        "261.433",
        "246.868"
      ],
      "Şehir": "Düzce",
      "Ücret": "Ücretsiz"
    },
    {
      "Program Kodu": "109750692",
      "Üniversite": "Bursa Uludağ Üniversitesi",
      "Fakülte": "Mustafakemalpaşa Meslek Yüksekokulu",
      "Üniversite Türü": "Devlet",
      "Program Adı": "G",
      "Öğretim Türü": "Örgün",
      "Yıl": [
        "2025",
        "2024",
        "2023",
        "2022",
        "2021"
      ],
      "Kontenjan": [
        "30+1+0+0+040+1+0+0+040+1+0+1+0--"
      ],
      "Yerleşen": [
        "41+0+0+0+0",
        "Doldu-42"
      ],
      "Taban Sıralama": [
        "1,472",
        "371,627"
      ],
      "Taban Puan": [
        "260.574",
        "249.225"
      ],
      "Şehir": "Bursa",
      "Ücret": "Ücretsiz"
    },
    {
      "Program Kodu": "101950078",
      "Üniversite": "Bilecik Şeyh Edebali Üniversitesi",
      "Fakülte": "Meslek Yüksekokulu",
      "Üniversite Türü": "Devlet",
      "Program Adı": "G",
      "Öğretim Türü": "Örgün",
      "Yıl": [
        "2025",
        "2024",
        "2023",
        "2022",
        "2021"
      ],
      "Kontenjan": [
        "35+1+0+1+040+1+0+1+040+1+0+1+0--"
      ],
      "Yerleşen": [
        "41+0+0+1+0",
        "Doldu-42"
      ],
      "Taban Sıralama": [
        "1,454",
        "141,686"
      ],
      "Taban Puan": [
        "261.674",
        "245.871"
      ],
      "Şehir": "Bilecik",
      "Ücret": "Ücretsiz"
    },
    {
      "Program Kodu": "109950275",
      "Üniversite": "Yalova Üniversitesi",
      "Fakülte": "Armutlu Meslek Yüksekokulu",
      "Üniversite Türü": "Devlet",
      "Program Adı": "G",
      "Öğretim Türü": "Örgün",
      "Yıl": [
        "2025",
        "2024",
        "2023",
        "2022",
        "2021"
      ],
      "Kontenjan": [
        "35+1+0+1+040+1+0+1+040+1+0+1+0--"
      ],
      "Yerleşen": [
        "40+1+0+1+0",
        "Doldu-42"
      ],
      "Taban Sıralama": [
        "1,501",
        "001,629"
      ],
      "Taban Puan": [
        "258.839",
        "249.15"
      ],
      "Şehir": "Yalova",
      "Ücret": "Ücretsiz"
    },
    {
      "Program Kodu": "112070690",
      "Üniversite": "Tarsus Üniversitesi",
      "Fakülte": "Mersin Tarsus Organize Sanayi Bölgesi Teknik Bilimler Meslek Yüksekokulu",
      "Üniversite Türü": "Devlet",
      "Program Adı": "G",
      "Öğretim Türü": "Örgün",
      "Yıl": [
        "2025",
        "2024",
        "2023",
        "2022",
        "2021"
      ],
      "Kontenjan": [
        "35+1+0+1+040+1+0+1+040+1+0+1+0--"
      ],
      "Yerleşen": [
        "41+0+0+1+0",
        "Doldu-42"
      ],
      "Taban Sıralama": [
        "1,516",
        "861,583"
      ],
      "Taban Puan": [
        "257.952",
        "251.834"
      ],
      "Şehir": "Mersin",
      "Ücret": "Ücretsiz"
    },
    {
      "Program Kodu": "101450832",
      "Üniversite": "Atatürk Üniversitesi",
      "Fakülte": "Teknik Bilimler Meslek Yüksekokulu",
      "Üniversite Türü": "Devlet",
      "Program Adı": "G",
      "Öğretim Türü": "Örgün",
      "Yıl": [
        "2025",
        "2024",
        "2023",
        "2022",
        "2021"
      ],
      "Kontenjan": [
        "35+1+0+0+040+1+0+0+040+1+0+1+0--"
      ],
      "Yerleşen": [
        "41+0+0+0+0",
        "Doldu-42"
      ],
      "Taban Sıralama": [
        "1,530",
        "711,638"
      ],
      "Taban Puan": [
        "257.105",
        "248.617"
      ],
      "Şehir": "Erzurum",
      "Ücret": "Ücretsiz"
    },
    {
      "Program Kodu": "100351825",
      "Üniversite": "Aydın Adnan Menderes Üniversitesi",
      "Fakülte": "Köşk Meslek Yüksekokulu",
      "Üniversite Türü": "Devlet",
      "Program Adı": "G",
      "Öğretim Türü": "Örgün",
      "Yıl": [
        "2025",
        "2024",
        "2023",
        "2022",
        "2021"
      ],
      "Kontenjan": [
        "35+1+0+1+075+2+0+2+075+2+0+2+0--"
      ],
      "Yerleşen": [
        "77+0+0+2+0",
        "77"
      ],
      "Taban Sıralama": [
        "1,531"
      ],
      "Taban Puan": [
        "257.071"
      ],
      "Şehir": "Aydın",
      "Ücret": "Ücretsiz"
    },
    {
      "Program Kodu": "109750859",
      "Üniversite": "Bursa Uludağ Üniversitesi",
      "Fakülte": "Yenişehir İbrahim Orhan Meslek Yüksekokulu",
      "Üniversite Türü": "Devlet",
      "Program Adı": "G",
      "Öğretim Türü": "Örgün",
      "Yıl": [
        "2025",
        "2024",
        "2023",
        "2022",
        "2021"
      ],
      "Kontenjan": [
        "30+1+0+0+045+2+0+0+045+2+0+2+0--"
      ],
      "Yerleşen": [
        "47+0+0+0+0",
        "Doldu-49"
      ],
      "Taban Sıralama": [
        "1,536",
        "151,680"
      ],
      "Taban Puan": [
        "256.767",
        "246.186"
      ],
      "Şehir": "Bursa",
      "Ücret": "Ücretsiz"
    },
    {
      "Program Kodu": "105390344",
      "Üniversite": "İnönü Üniversitesi",
      "Fakülte": "Malatya Osb Meslek Yüksekokulu",
      "Üniversite Türü": "Devlet",
      "Program Adı": "G",
      "Öğretim Türü": "Örgün",
      "Yıl": [
        "2025",
        "2024",
        "2023",
        "2022",
        "2021"
      ],
      "Kontenjan": [
        "30+1+0+1+330+1+0+1+830+1+0+1+8--"
      ],
      "Yerleşen": [
        "31+0+0+1+8",
        "Doldu-40"
      ],
      "Taban Sıralama": [
        "1,537",
        "081,678"
      ],
      "Taban Puan": [
        "256.691",
        "246.302"
      ],
      "Şehir": "Malatya",
      "Ücret": "Ücretsiz"
    },
    {
      "Program Kodu": "106251174",
      "Üniversite": "Karadeniz Teknik Üniversitesi",
      "Fakülte": "Maçka Meslek Yüksekokulu",
      "Üniversite Türü": "Devlet",
      "Program Adı": "G",
      "Öğretim Türü": "Örgün",
      "Yıl": [
        "2025",
        "2024",
        "2023",
        "2022",
        "2021"
      ],
      "Kontenjan": [
        "35+1+0+0+035+1+0+0+035+1+0+1+0--"
      ],
      "Yerleşen": [
        "36+0+0+0+0",
        "Doldu-37"
      ],
      "Taban Sıralama": [
        "1,569",
        "291,687"
      ],
      "Taban Puan": [
        "254.847",
        "245.793"
      ],
      "Şehir": "Trabzon",
      "Ücret": "Ücretsiz"
    },
    {
      "Program Kodu": "108250522",
      "Üniversite": "Ondokuz Mayıs Üniversitesi",
      "Fakülte": "Terme Meslek Yüksekokulu",
      "Üniversite Türü": "Devlet",
      "Program Adı": "G",
      "Öğretim Türü": "Örgün",
      "Yıl": [
        "2025",
        "2024",
        "2023",
        "2022",
        "2021"
      ],
      "Kontenjan": [
        "35+1+0+1+040+1+0+1+040+1+0+1+0--"
      ],
      "Yerleşen": [
        "41+0+0+1+0",
        "41"
      ],
      "Taban Sıralama": [
        "1,570"
      ],
      "Taban Puan": [
        "254.756"
      ],
      "Şehir": "Samsun",
      "Ücret": "Ücretsiz"
    },
    {
      "Program Kodu": "106350024",
      "Üniversite": "Karamanoğlu Mehmetbey Üniversitesi",
      "Fakülte": "Teknik Bilimler Meslek Yüksekokulu",
      "Üniversite Türü": "Devlet",
      "Program Adı": "G",
      "Öğretim Türü": "Örgün",
      "Yıl": [
        "2025",
        "2024",
        "2023",
        "2022",
        "2021"
      ],
      "Kontenjan": [
        "35+1+0+1+055+2+0+2+055+2+0+2+0--"
      ],
      "Yerleşen": [
        "57+0+0+2+0",
        "Doldu-59"
      ],
      "Taban Sıralama": [
        "1,577",
        "121,712"
      ],
      "Taban Puan": [
        "254.371",
        "244.396"
      ],
      "Şehir": "Karaman",
      "Ücret": "Ücretsiz"
    },
    {
      "Program Kodu": "107351028",
      "Üniversite": "Burdur Mehmet Akif Ersoy Üniversitesi",
      "Fakülte": "Burdur Gıda Tarım Ve Hayvancılık Meslek Yüksekokulu",
      "Üniversite Türü": "Devlet",
      "Program Adı": "G",
      "Öğretim Türü": "Örgün",
      "Yıl": [
        "2025",
        "2024",
        "2023",
        "2022",
        "2021"
      ],
      "Kontenjan": [
        "35+1+0+1+040+1+0+1+040+1+0+1+0--"
      ],
      "Yerleşen": [
        "41+0+0+1+0",
        "Doldu-42"
      ],
      "Taban Sıralama": [
        "1,543",
        "961,700"
      ],
      "Taban Puan": [
        "256.382",
        "45.083"
      ],
      "Şehir": "Burdur",
      "Ücret": "Ücretsiz"
    },
    {
      "Program Kodu": "206050511",
      "Üniversite": "Yaşar Üniversitesi",
      "Fakülte": "Meslek Yüksekokulu",
      "Üniversite Türü": "Vakıf",
      "Program Adı": "G",
      "Öğretim Türü": "Örgün",
      "Yıl": [
        "2025",
        "2024",
        "2023",
        "2022",
        "2021"
      ],
      "Kontenjan": [
        "37+0+0+0+036+0+0+0+035+0+0+0+0--"
      ],
      "Yerleşen": [
        "36+0+0+0+0",
        "Doldu-35"
      ],
      "Taban Sıralama": [
        "1,584",
        "461,895"
      ],
      "Taban Puan": [
        "253.947",
        "234.352"
      ],
      "Şehir": "İzmir",
      "Ücret": "%50 İndirimli"
    }
  ]
}