{
  "yks": [
    {
      "Program Kodu": "203111033",
      "Üniversite": "İstanbul Medipol Üniversitesi",
      "Fakülte": "Sağlık Bilimleri Yüksekokulu",
      "Üniversite Türü": "Vakıf",
      "Program Adı": "F",
      "Öğretim Türü": "Örgün",
      "Yıl": [
        "2025",
        "2024",
        "2023",
        "2022",
        "2021"
      ],
      "Kontenjan": [
        "10+0+2+0+110+0+1+0+110+0+1+0+19+012+0"
      ],
      "Yerleşen": [
        "11",
        "10+0+0+0+1",
        "11912"
      ],
      "Taban Sıralama": [
        "213,902",
        "195,421",
        "154,215",
        "175,721"
      ],
      "Taban Puan": [
        "317.843",
        "346.763",
        "363.232",
        "293.641"
      ],
      "Şehir": "İstanbul",
      "Ücret": "Burslu"
    },
    {
      "Program Kodu": "203851854",
      "Üniversite": "Kapadokya Üniversitesi",
      "Fakülte": "Sağlık Bilimleri Yüksekokulu",
      "Üniversite Türü": "Vakıf",
      "Program Adı": "F",
      "Öğretim Türü": "Örgün",
      "Yıl": [
        "2025",
        "2024",
        "2023",
        "2022",
        "2021"
      ],
      "Kontenjan": [
        "7+0+1+0+17+0+1+0+17+0+1+0+18+09+0"
      ],
      "Yerleşen": [
        "8",
        "7+0+0+0+1",
        "889"
      ],
      "Taban Sıralama": [
        "323,773",
        "309,286",
        "291,060",
        "289,156"
      ],
      "Taban Puan": [
        "284.244",
        "305.013",
        "300.809",
        "250.834"
      ],
      "Şehir": "Nevşehir",
      "Ücret": "Burslu"
    },
    {
      "Program Kodu": "100610261",
      "Üniversite": "Kırşehir Ahi Evran Üniversitesi",
      "Fakülte": "Fizik Tedavi Ve Rehabilitasyon Yüksekokulu",
      "Üniversite Türü": "Devlet",
      "Program Adı": "F",
      "Öğretim Türü": "Örgün",
      "Yıl": [
        "2025",
        "2024",
        "2023",
        "2022",
        "2021"
      ],
      "Kontenjan": [
        "65+2+0+2+085+3+0+3+080+2+0+2+080+280+2"
      ],
      "Yerleşen": [
        "91",
        "85+3+0+3+0",
        "838282"
      ],
      "Taban Sıralama": [
        "362,902",
        "361,626",
        "321,370",
        "334,254"
      ],
      "Taban Puan": [
        "275.648",
        "291.562",
        "91.456",
        "239.135"
      ],
      "Şehir": "Kırşehir",
      "Ücret": "Ücretsiz"
    },
    {
      "Program Kodu": "108710378",
      "Üniversite": "Recep Tayyip Erdoğan Üniversitesi",
      "Fakülte": "Güneysu Fizik Tedavi Ve Rehabilitasyon Yüksekokulu",
      "Üniversite Türü": "Devlet",
      "Program Adı": "F",
      "Öğretim Türü": "Örgün",
      "Yıl": [
        "2025",
        "2024",
        "2023",
        "2022",
        "2021"
      ],
      "Kontenjan": [
        "40+1+0+1+075+2+0+2+070+2+0+2+070+270+2"
      ],
      "Yerleşen": [
        "79",
        "75+2+0+2+0",
        "747272"
      ],
      "Taban Sıralama": [
        "365,529",
        "355,969",
        "321,382",
        "334,910"
      ],
      "Taban Puan": [
        "275.132",
        "292.891",
        "291.452",
        "238.975"
      ],
      "Şehir": "Rize",
      "Ücret": "Ücretsiz"
    },
    {
      "Program Kodu": "102390104",
      "Üniversite": "Yozgat Bozok Üniversitesi",
      "Fakülte": "Sarıkaya Fizyoterapi Ve Rehabilitasyon Yüksekokulu",
      "Üniversite Türü": "Devlet",
      "Program Adı": "F",
      "Öğretim Türü": "Örgün",
      "Yıl": [
        "2025",
        "2024",
        "2023",
        "2022",
        "2021"
      ],
      "Kontenjan": [
        "40+1+0+1+075+2+0+2+070+2+0+2+070+265+2"
      ],
      "Yerleşen": [
        "79",
        "76+1+0+2+0",
        "727267"
      ],
      "Taban Sıralama": [
        "384,593",
        "382,801",
        "336,966",
        "323,600"
      ],
      "Taban Puan": [
        "271.395",
        "286.728",
        "287.096",
        "241.694"
      ],
      "Şehir": "Yozgat",
      "Ücret": "Ücretsiz"
    },
    {
      "Program Kodu": "203851978",
      "Üniversite": "Kapadokya Üniversitesi",
      "Fakülte": "Sağlık Bilimleri Yüksekokulu",
      "Üniversite Türü": "Vakıf",
      "Program Adı": "F",
      "Öğretim Türü": "Örgün",
      "Yıl": [
        "2025",
        "2024",
        "2023",
        "2022",
        "2021"
      ],
      "Kontenjan": [
        "42+0+0+0+042+0+0+0+042+0+0+0+042+0-"
      ],
      "Yerleşen": [
        "42",
        "42+0+0+0+0",
        "4242"
      ],
      "Taban Sıralama": [
        "747,237",
        "639,493",
        "644,898"
      ],
      "Taban Puan": [
        "229.912",
        "246.677",
        "234.744"
      ],
      "Şehir": "Nevşehir",
      "Ücret": "%50 İndirimli"
    }
  ]
}