{
  "yks": [
    {
      "Program Kodu": "203910275",
      "Üniversite": "Koç Üniversitesi",
      "Fakülte": "İktisadi Ve İdari Bilimler Fakültesi",
      "Üniversite Türü": "Vakıf",
      "Program Adı": "E",
      "Öğretim Türü": "Örgün",
      "Yıl": [
        "2025",
        "2024",
        "2023",
        "2022",
        "2021"
      ],
      "Kontenjan": [
        "19+0+2+0+116+0+2+0+116+0+3+0+119+016+0"
      ],
      "Yerleşen": [
        "19",
        "16+0+2+0+1",
        "201916"
      ],
      "Taban Sıralama": [],
      "Taban Puan": [
        "527.813",
        "537.573",
        "526.157",
        "501.537"
      ],
      "Şehir": "İstanbul",
      "Ücret": "Burslu"
    },
    {
      "Program Kodu": "204810334",
      "Üniversite": "Özyeğin Üniversitesi",
      "Fakülte": "İşletme Fakültesi",
      "Üniversite Türü": "Vakıf",
      "Program Adı": "E",
      "Öğretim Türü": "Örgün",
      "Yıl": [
        "2025",
        "2024",
        "2023",
        "2022",
        "2021"
      ],
      "Kontenjan": [
        "9+0+1+0+16+0+1+0+16+0+1+0+16+06+0"
      ],
      "Yerleşen": [
        "8",
        "6+0+1+0+1",
        "766"
      ],
      "Taban Sıralama": [
        "141,278"
      ],
      "Taban Puan": [
        "497.137",
        "506.871",
        "498.423",
        "451.692"
      ],
      "Şehir": "İstanbul",
      "Ücret": "Burslu"
    },
    {
      "Program Kodu": "105511051",
      "Üniversite": "İstanbul Teknik Üniversitesi",
      "Fakülte": "İşletme Fakültesi",
      "Üniversite Türü": "Devlet",
      "Program Adı": "E",
      "Öğretim Türü": "Örgün",
      "Yıl": [
        "2025",
        "2024",
        "2023",
        "2022",
        "2021"
      ],
      "Kontenjan": [
        "35+1+0+0+035+1+0+0+040+1+0+1+040+160+2"
      ],
      "Yerleşen": [
        "36",
        "35+1+0+0+0",
        "424162"
      ],
      "Taban Sıralama": [
        "1,608",
        "1,803",
        "2,785",
        "5,476"
      ],
      "Taban Puan": [
        "475.941",
        "487.497",
        "480.664",
        "410.849"
      ],
      "Şehir": "İstanbul",
      "Ücret": "Ücretsiz"
    },
    {
      "Program Kodu": "206190353",
      "Üniversite": "Yeditepe Üniversitesi",
      "Fakülte": "İktisadi Ve İdari Bilimler Fakültesi",
      "Üniversite Türü": "Vakıf",
      "Program Adı": "E",
      "Öğretim Türü": "Örgün",
      "Yıl": [
        "2025",
        "2024",
        "2023",
        "2022",
        "2021"
      ],
      "Kontenjan": [
        "7+0+1+0+17+0+1+0+16+0+1+0+16+06+0"
      ],
      "Yerleşen": [
        "9",
        "7+0+1+0+1",
        "766"
      ],
      "Taban Sıralama": [
        "1,900",
        "1,990",
        "2,929",
        "6,429"
      ],
      "Taban Puan": [
        "471.357",
        "485.042",
        "479.354",
        "406.784"
      ],
      "Şehir": "İstanbul",
      "Ücret": "Burslu"
    },
    {
      "Program Kodu": "200510322",
      "Üniversite": "Bahçeşehir Üniversitesi",
      "Fakülte": "İktisadi, İdari Ve Sosyal Bilimler Fakültesi",
      "Üniversite Türü": "Vakıf",
      "Program Adı": "E",
      "Öğretim Türü": "Örgün",
      "Yıl": [
        "2025",
        "2024",
        "2023",
        "2022",
        "2021"
      ],
      "Kontenjan": [
        "10+0+2+0+18+0+1+0+18+0+1+0+19+09+0"
      ],
      "Yerleşen": [
        "10",
        "8+0+1+0+1",
        "999"
      ],
      "Taban Sıralama": [
        "2,793",
        "2,995",
        "4,798",
        "9,008"
      ],
      "Taban Puan": [
        "460.227",
        "473.474",
        "66.587",
        "398.22"
      ],
      "Şehir": "İstanbul",
      "Ücret": "Burslu"
    },
    {
      "Program Kodu": "203510261",
      "Üniversite": "İzmir Ekonomi Üniversitesi",
      "Fakülte": "İşletme Fakültesi",
      "Üniversite Türü": "Vakıf",
      "Program Adı": "E",
      "Öğretim Türü": "Örgün",
      "Yıl": [
        "2025",
        "2024",
        "2023",
        "2022",
        "2021"
      ],
      "Kontenjan": [
        "6+0+1+0+16+0+1+0+14+0+1+0+14+04+0"
      ],
      "Yerleşen": [
        "8",
        "6+0+1+0+1",
        "544"
      ],
      "Taban Sıralama": [
        "4,159",
        "3,400",
        "13,150",
        "23,385"
      ],
      "Taban Puan": [
        "450.594",
        "469.748",
        "437.893",
        "372.742"
      ],
      "Şehir": "İzmir",
      "Ücret": "Burslu"
    },
    {
      "Program Kodu": "200511056",
      "Üniversite": "Bahçeşehir Üniversitesi",
      "Fakülte": "İktisadi, İdari Ve Sosyal Bilimler Fakültesi",
      "Üniversite Türü": "Vakıf",
      "Program Adı": "E",
      "Öğretim Türü": "Örgün",
      "Yıl": [
        "2025",
        "2024",
        "2023",
        "2022",
        "2021"
      ],
      "Kontenjan": [
        "10+0+1+0+16+0+1+0+16+0+1+0+17+06+0"
      ],
      "Yerleşen": [
        "8",
        "6+0+1+0+1",
        "776"
      ],
      "Taban Sıralama": [
        "5,687",
        "4,910",
        "7,338",
        "11,226"
      ],
      "Taban Puan": [
        "444.261",
        "457.962",
        "454.922",
        "392.615"
      ],
      "Şehir": "İstanbul",
      "Ücret": "Burslu"
    },
    {
      "Program Kodu": "202510201",
      "Üniversite": "İstanbul Bilgi Üniversitesi",
      "Fakülte": "İşletme Fakültesi",
      "Üniversite Türü": "Vakıf",
      "Program Adı": "E",
      "Öğretim Türü": "Örgün",
      "Yıl": [
        "2025",
        "2024",
        "2023",
        "2022",
        "2021"
      ],
      "Kontenjan": [
        "14+0+2+0+113+0+2+0+112+0+2+0+113+011+0"
      ],
      "Yerleşen": [
        "14",
        "13+0+0+0+1",
        "131311"
      ],
      "Taban Sıralama": [
        "7,963",
        "4,185",
        "7,173",
        "8,760"
      ],
      "Taban Puan": [
        "437.119",
        "463.294",
        "455.662",
        "398.938"
      ],
      "Şehir": "İstanbul",
      "Ücret": "Burslu"
    },
    {
      "Program Kodu": "203710108",
      "Üniversite": "Kadir Has Üniversitesi",
      "Fakülte": "İktisadi, İdari Ve Sosyal Bilimler Fakültesi",
      "Üniversite Türü": "Vakıf",
      "Program Adı": "E",
      "Öğretim Türü": "Örgün",
      "Yıl": [
        "2025",
        "2024",
        "2023",
        "2022",
        "2021"
      ],
      "Kontenjan": [
        "4+0+1+0+14+0+1+0+15+0+1+0+14+04+0"
      ],
      "Yerleşen": [
        "5",
        "4+0+0+0+1",
        "644"
      ],
      "Taban Sıralama": [
        "9,088",
        "9,090",
        "12,996",
        "21,725"
      ],
      "Taban Puan": [
        "434.268",
        "438.946",
        "438.228",
        "374.924"
      ],
      "Şehir": "İstanbul",
      "Ücret": "Burslu"
    },
    {
      "Program Kodu": "207210013",
      "Üniversite": "Mef Üniversitesi",
      "Fakülte": "İktisadi, İdari Ve Sosyal Bilimler Fakültesi",
      "Üniversite Türü": "Vakıf",
      "Program Adı": "E",
      "Öğretim Türü": "Örgün",
      "Yıl": [
        "2025",
        "2024",
        "2023",
        "2022",
        "2021"
      ],
      "Kontenjan": [
        "3+0+1+0+13+0+1+0+13+0+1+0+14+04+0"
      ],
      "Yerleşen": [
        "5",
        "3+0+1+0+1",
        "444"
      ],
      "Taban Sıralama": [
        "10,851",
        "5,638",
        "8,404",
        "13,822"
      ],
      "Taban Puan": [
        "430.502",
        "453.707",
        "450.793",
        "387.278"
      ],
      "Şehir": "İstanbul",
      "Ücret": "Burslu"
    },
    {
      "Program Kodu": "202590229",
      "Üniversite": "İstanbul Bilgi Üniversitesi",
      "Fakülte": "İşletme Fakültesi",
      "Üniversite Türü": "Vakıf",
      "Program Adı": "E",
      "Öğretim Türü": "Örgün",
      "Yıl": [
        "2025",
        "2024",
        "2023",
        "2022",
        "2021"
      ],
      "Kontenjan": [
        "15+0+2+0+114+0+2+0+113+0+2+0+113+012+0"
      ],
      "Yerleşen": [
        "15",
        "14+0+0+0+1",
        "141312"
      ],
      "Taban Sıralama": [
        "20,794",
        "8,726",
        "10,155",
        "13,236"
      ],
      "Taban Puan": [
        "414.689",
        "440.208",
        "445.179",
        "388.459"
      ],
      "Şehir": "İstanbul",
      "Ücret": "Burslu"
    },
    {
      "Program Kodu": "206010133",
      "Üniversite": "Yaşar Üniversitesi",
      "Fakülte": "İşletme Fakültesi",
      "Üniversite Türü": "Vakıf",
      "Program Adı": "E",
      "Öğretim Türü": "Örgün",
      "Yıl": [
        "2025",
        "2024",
        "2023",
        "2022",
        "2021"
      ],
      "Kontenjan": [
        "5+0+1+0+15+0+1+0+14+0+1+0+13+04+0"
      ],
      "Yerleşen": [
        "6",
        "5+0+0+0+1",
        "634"
      ],
      "Taban Sıralama": [
        "46,723",
        "54,885",
        "77,499",
        "81,558"
      ],
      "Taban Puan": [
        "390.071",
        "394.023",
        "89.415",
        "329.295"
      ],
      "Şehir": "İzmir",
      "Ücret": "Burslu"
    },
    {
      "Program Kodu": "101190339",
      "Üniversite": "Ankara Üniversitesi",
      "Fakülte": "Siyasal Bilgiler Fakültesi",
      "Üniversite Türü": "Devlet",
      "Program Adı": "P",
      "Öğretim Türü": "Örgün",
      "Yıl": [
        "2025",
        "2024",
        "2023",
        "2022",
        "2021"
      ],
      "Kontenjan": [
        "40+1+0+0+045+2+0+0+040+1+0+1+040+140+1"
      ],
      "Yerleşen": [
        "47",
        "45+2+0+0+0",
        "414141"
      ],
      "Taban Sıralama": [
        "48,656",
        "59,867",
        "86,858",
        "84,284"
      ],
      "Taban Puan": [
        "388.652",
        "391.195",
        "384.835",
        "327.909"
      ],
      "Şehir": "Ankara",
      "Ücret": "Ücretsiz"
    },
    {
      "Program Kodu": "203110671",
      "Üniversite": "İstanbul Medipol Üniversitesi",
      "Fakülte": "İşletme Ve Yönetim Bilimleri Fakültesi",
      "Üniversite Türü": "Vakıf",
      "Program Adı": "E",
      "Öğretim Türü": "Örgün",
      "Yıl": [
        "2025",
        "2024",
        "2023",
        "2022",
        "2021"
      ],
      "Kontenjan": [
        "8+0+1+0+18+0+1+0+17+0+1+0+17+06+0"
      ],
      "Yerleşen": [
        "9",
        "8+0+0+0+1",
        "876"
      ],
      "Taban Sıralama": [
        "85,744",
        "110,955",
        "114,300",
        "107,141"
      ],
      "Taban Puan": [
        "366.884",
        "367.438",
        "372.627",
        "317.071"
      ],
      "Şehir": "İstanbul",
      "Ücret": "Burslu"
    },
    {
      "Program Kodu": "208450765",
      "Üniversite": "İstinye Üniversitesi",
      "Fakülte": "İktisadi, İdari Ve Sosyal Bilimler Fakültesi",
      "Üniversite Türü": "Vakıf",
      "Program Adı": "E",
      "Öğretim Türü": "Örgün",
      "Yıl": [
        "2025",
        "2024",
        "2023",
        "2022",
        "2021"
      ],
      "Kontenjan": [
        "4+0+1+0+14+0+1+0+14+0+1+0+15+014+0"
      ],
      "Yerleşen": [
        "5",
        "4+0+0+0+1",
        "5514"
      ],
      "Taban Sıralama": [
        "135,269",
        "165,246",
        "190,650",
        "241,595"
      ],
      "Taban Puan": [
        "346.776",
        "348.802",
        "345.599",
        "275.191"
      ],
      "Şehir": "İstanbul",
      "Ücret": "Burslu"
    },
    {
      "Program Kodu": "206410059",
      "Üniversite": "Antalya Bilim Üniversitesi",
      "Fakülte": "İktisadi, İdari Ve Sosyal Bilimler Fakültesi",
      "Üniversite Türü": "Vakıf",
      "Program Adı": "E",
      "Öğretim Türü": "Örgün",
      "Yıl": [
        "2025",
        "2024",
        "2023",
        "2022",
        "2021"
      ],
      "Kontenjan": [
        "5+0+1+0+14+0+1+0+14+0+1+0+13+05+0"
      ],
      "Yerleşen": [
        "5",
        "4+0+0+0+1",
        "535"
      ],
      "Taban Sıralama": [
        "139,847",
        "160,664",
        "159,902",
        "201,016"
      ],
      "Taban Puan": [
        "345.211",
        "350.197",
        "355.442",
        "85.162"
      ],
      "Şehir": "Antalya",
      "Ücret": "Burslu"
    },
    {
      "Program Kodu": "204910245",
      "Üniversite": "Piri Reis Üniversitesi",
      "Fakülte": "İktisadi Ve İdari Bilimler Fakültesi",
      "Üniversite Türü": "Vakıf",
      "Program Adı": "E",
      "Öğretim Türü": "Örgün",
      "Yıl": [
        "2025",
        "2024",
        "2023",
        "2022",
        "2021"
      ],
      "Kontenjan": [
        "4+0+1+0+14+0+1+0+14+0+1+0+13+05+0"
      ],
      "Yerleşen": [
        "5",
        "4+0+0+0+1",
        "435"
      ],
      "Taban Sıralama": [
        "141,779",
        "142,929",
        "182,677",
        "231,061"
      ],
      "Taban Puan": [
        "344.569",
        "355.833",
        "348.019",
        "277.666"
      ],
      "Şehir": "İstanbul",
      "Ücret": "Burslu"
    },
    {
      "Program Kodu": "101190731",
      "Üniversite": "Ankara Üniversitesi",
      "Fakülte": "Siyasal Bilgiler Fakültesi",
      "Üniversite Türü": "Devlet",
      "Program Adı": "Ç",
      "Öğretim Türü": "Örgün",
      "Yıl": [
        "2025",
        "2024",
        "2023",
        "2022",
        "2021"
      ],
      "Kontenjan": [
        "30+1+0+0+0----"
      ],
      "Yerleşen": [],
      "Taban Sıralama": [
        "145,431"
      ],
      "Taban Puan": [
        "343.387"
      ],
      "Şehir": "Ankara",
      "Ücret": "Ücretsiz"
    },
    {
      "Program Kodu": "204810343",
      "Üniversite": "Özyeğin Üniversitesi",
      "Fakülte": "İşletme Fakültesi",
      "Üniversite Türü": "Vakıf",
      "Program Adı": "E",
      "Öğretim Türü": "Örgün",
      "Yıl": [
        "2025",
        "2024",
        "2023",
        "2022",
        "2021"
      ],
      "Kontenjan": [
        "22+0+0+0+022+0+0+0+027+0+0+0+029+032+0"
      ],
      "Yerleşen": [
        "22",
        "22+0+0+0+0",
        "272932"
      ],
      "Taban Sıralama": [
        "157,506",
        "170,090",
        "182,338",
        "222,797"
      ],
      "Taban Puan": [
        "339.516",
        "347.411",
        "348.125",
        "279.646"
      ],
      "Şehir": "İstanbul",
      "Ücret": "%50 İndirimli"
    },
    {
      "Program Kodu": "110910086",
      "Üniversite": "Ankara Sosyal Bilimler Üniversitesi",
      "Fakülte": "Siyasal Bilgiler Fakültesi",
      "Üniversite Türü": "Devlet",
      "Program Adı": "E",
      "Öğretim Türü": "Örgün",
      "Yıl": [
        "2025",
        "2024",
        "2023",
        "2022",
        "2021"
      ],
      "Kontenjan": [
        "40+1+0+1+070+2+0+2+060+2+0+2+060+260+2"
      ],
      "Yerleşen": [
        "74",
        "72+0+0+2+0",
        "626262"
      ],
      "Taban Sıralama": [
        "161,838",
        "184,105",
        "221,932",
        "236,059"
      ],
      "Taban Puan": [
        "338.209",
        "343.455",
        "336.842",
        "276.468"
      ],
      "Şehir": "Ankara",
      "Ücret": "Ücretsiz"
    },
    {
      "Program Kodu": "209110041",
      "Üniversite": "Ostim Teknik Üniversitesi",
      "Fakülte": "İktisadi Ve İdari Bilimler Fakültesi",
      "Üniversite Türü": "Vakıf",
      "Program Adı": "E",
      "Öğretim Türü": "Örgün",
      "Yıl": [
        "2025",
        "2024",
        "2023",
        "2022",
        "2021"
      ],
      "Kontenjan": [
        "7+0+1+0+16+0+1+0+14+0+1+0+15+05+0"
      ],
      "Yerleşen": [
        "7",
        "6+0+0+0+1",
        "555"
      ],
      "Taban Sıralama": [
        "176,543",
        "194,612",
        "251,888",
        "274,633"
      ],
      "Taban Puan": [
        "334.024",
        "340.737",
        "329.461",
        "268.271"
      ],
      "Şehir": "Ankara",
      "Ücret": "Burslu"
    },
    {
      "Program Kodu": "202210213",
      "Üniversite": "İstanbul 29 Mayıs Üniversitesi",
      "Fakülte": "İktisadi Ve İdari Bilimler Fakültesi",
      "Üniversite Türü": "Vakıf",
      "Program Adı": "E",
      "Öğretim Türü": "Örgün",
      "Yıl": [
        "2025",
        "2024",
        "2023",
        "2022",
        "2021"
      ],
      "Kontenjan": [
        "8+0+1+0+19+0+1+0+16+0+1+0+15+05+0"
      ],
      "Yerleşen": [
        "10",
        "9+0+0+0+1",
        "755"
      ],
      "Taban Sıralama": [
        "183,110",
        "132,695",
        "115,505",
        "106,028"
      ],
      "Taban Puan": [
        "332.267",
        "359.346",
        "372.118",
        "317.569"
      ],
      "Şehir": "İstanbul",
      "Ücret": "Burslu"
    },
    {
      "Program Kodu": "202490828",
      "Üniversite": "İstanbul Aydın Üniversitesi",
      "Fakülte": "İktisadi Ve İdari Bilimler Fakültesi",
      "Üniversite Türü": "Vakıf",
      "Program Adı": "E",
      "Öğretim Türü": "Örgün",
      "Yıl": [
        "2025",
        "2024",
        "2023",
        "2022",
        "2021"
      ],
      "Kontenjan": [
        "5+0+1+0+14+0+1+0+1---"
      ],
      "Yerleşen": [
        "5",
        "4+0+0+0+1"
      ],
      "Taban Sıralama": [
        "185,248"
      ],
      "Taban Puan": [
        "331.716"
      ],
      "Şehir": "İstanbul",
      "Ücret": "Burslu"
    },
    {
      "Program Kodu": "202410856",
      "Üniversite": "İstanbul Aydın Üniversitesi",
      "Fakülte": "İktisadi Ve İdari Bilimler Fakültesi",
      "Üniversite Türü": "Vakıf",
      "Program Adı": "E",
      "Öğretim Türü": "Örgün",
      "Yıl": [
        "2025",
        "2024",
        "2023",
        "2022",
        "2021"
      ],
      "Kontenjan": [
        "8+0+1+0+17+0+1+0+15+0+1+0+15+07+0"
      ],
      "Yerleşen": [
        "8",
        "7+0+0+0+1",
        "657"
      ],
      "Taban Sıralama": [
        "187,750",
        "187,803",
        "237,021",
        "252,517"
      ],
      "Taban Puan": [
        "331.058",
        "342.482",
        "333.027",
        "272.797"
      ],
      "Şehir": "İstanbul",
      "Ücret": "Burslu"
    },
    {
      "Program Kodu": "209010170",
      "Üniversite": "Fenerbahçe Üniversitesi",
      "Fakülte": "İktisadi, İdari Ve Sosyal Bilimler Fakültesi",
      "Üniversite Türü": "Vakıf",
      "Program Adı": "E",
      "Öğretim Türü": "Örgün",
      "Yıl": [
        "2025",
        "2024",
        "2023",
        "2022",
        "2021"
      ],
      "Kontenjan": [
        "4+0+1+0+14+0+1+0+14+0+1+0+15+0-"
      ],
      "Yerleşen": [
        "5",
        "4+0+0+0+1",
        "55"
      ],
      "Taban Sıralama": [
        "188,165",
        "170,740",
        "193,187"
      ],
      "Taban Puan": [
        "330.954",
        "347.221",
        "344.833"
      ],
      "Şehir": "İstanbul",
      "Ücret": "Burslu"
    },
    {
      "Program Kodu": "204713171",
      "Üniversite": "İstanbul Okan Üniversitesi",
      "Fakülte": "İşletme Ve Yönetim Bilimleri Fakültesi",
      "Üniversite Türü": "Vakıf",
      "Program Adı": "E",
      "Öğretim Türü": "Örgün",
      "Yıl": [
        "2025",
        "2024",
        "2023",
        "2022",
        "2021"
      ],
      "Kontenjan": [
        "9+0+1+0+19+0+1+0+15+0+1+0+15+04+0"
      ],
      "Yerleşen": [
        "9",
        "9+0+0+0+0",
        "654"
      ],
      "Taban Sıralama": [
        "192,669",
        "183,905",
        "205,928",
        "186,250"
      ],
      "Taban Puan": [
        "329.778",
        "343.511",
        "341.163",
        "289.204"
      ],
      "Şehir": "İstanbul",
      "Ücret": "Burslu"
    },
    {
      "Program Kodu": "105610519",
      "Üniversite": "İstanbul Üniversitesi",
      "Fakülte": "İktisat Fakültesi",
      "Üniversite Türü": "Devlet",
      "Program Adı": "Ç",
      "Öğretim Türü": "Örgün",
      "Yıl": [
        "2025",
        "2024",
        "2023",
        "2022",
        "2021"
      ],
      "Kontenjan": [
        "50+2+0+0+0105+3+0+0+0100+3+0+3+0100+3100+3"
      ],
      "Yerleşen": [
        "108",
        "105+3+0+0+0",
        "104103103"
      ],
      "Taban Sıralama": [
        "210,207",
        "252,480",
        "286,187",
        "300,146"
      ],
      "Taban Puan": [
        "325.575",
        "327.333",
        "21.881",
        "263.345"
      ],
      "Şehir": "İstanbul",
      "Ücret": "Ücretsiz"
    },
    {
      "Program Kodu": "202910463",
      "Üniversite": "Altınbaş Üniversitesi",
      "Fakülte": "İktisadi, İdari Ve Sosyal Bilimler Fakültesi",
      "Üniversite Türü": "Vakıf",
      "Program Adı": "E",
      "Öğretim Türü": "Örgün",
      "Yıl": [
        "2025",
        "2024",
        "2023",
        "2022",
        "2021"
      ],
      "Kontenjan": [
        "3+0+0+0+15+0+0+0+110+0+0+0+115+015+0"
      ],
      "Yerleşen": [
        "6",
        "5+0+0+0+1",
        "111515"
      ],
      "Taban Sıralama": [
        "213,906",
        "261,448",
        "277,477",
        "324,841"
      ],
      "Taban Puan": [
        "324.717",
        "325.492",
        "323.739",
        "258.945"
      ],
      "Şehir": "İstanbul",
      "Ücret": "Burslu"
    },
    {
      "Program Kodu": "107210359",
      "Üniversite": "Marmara Üniversitesi",
      "Fakülte": "İktisat Fakültesi",
      "Üniversite Türü": "Devlet",
      "Program Adı": "Ç",
      "Öğretim Türü": "Örgün",
      "Yıl": [
        "2025",
        "2024",
        "2023",
        "2022",
        "2021"
      ],
      "Kontenjan": [
        "45+2+0+0+095+3+0+0+090+3+0+3+090+390+3"
      ],
      "Yerleşen": [
        "98",
        "95+3+0+0+0",
        "969393"
      ],
      "Taban Sıralama": [
        "216,792",
        "248,391",
        "272,501",
        "278,493"
      ],
      "Taban Puan": [
        "324.065",
        "328.174",
        "324.825",
        "267.495"
      ],
      "Şehir": "İstanbul",
      "Ücret": "Ücretsiz"
    },
    {
      "Program Kodu": "202712946",
      "Üniversite": "İstanbul Gelişim Üniversitesi",
      "Fakülte": "İktisadi, İdari Ve Sosyal Bilimler Fakültesi",
      "Üniversite Türü": "Vakıf",
      "Program Adı": "E",
      "Öğretim Türü": "Örgün",
      "Yıl": [
        "2025",
        "2024",
        "2023",
        "2022",
        "2021"
      ],
      "Kontenjan": [
        "14+0+1+0+14+0+0+0+14+0+0+0+17+04+0"
      ],
      "Yerleşen": [
        "5",
        "4+0+0+0+1",
        "574"
      ],
      "Taban Sıralama": [
        "231,173",
        "229,280",
        "272,753",
        "248,966"
      ],
      "Taban Puan": [
        "320.876",
        "332.351",
        "324.769",
        "273.564"
      ],
      "Şehir": "İstanbul",
      "Ücret": "Burslu"
    },
    {
      "Program Kodu": "105590145",
      "Üniversite": "İstanbul Teknik Üniversitesi",
      "Fakülte": "İtü-Kktc Eğitim Araştırma Yerleşkesi (Gazimağusa)",
      "Üniversite Türü": "Devlet",
      "Program Adı": "E",
      "Öğretim Türü": "Örgün",
      "Yıl": [
        "2025",
        "2024",
        "2023",
        "2022",
        "2021"
      ],
      "Kontenjan": [
        "5+0+0+0+05+0+0+0+07+0+0+0+07+07+0"
      ],
      "Yerleşen": [
        "5",
        "5+0+0+0+0",
        "777"
      ],
      "Taban Sıralama": [
        "234,590",
        "30,421",
        "110,274",
        "414,867"
      ],
      "Taban Puan": [
        "320.141",
        "410.724",
        "374.333",
        "245.127"
      ],
      "Şehir": "İstanbul",
      "Ücret": "Burslu"
    },
    {
      "Program Kodu": "106510088",
      "Üniversite": "Abdullah Gül Üniversitesi",
      "Fakülte": "Yönetim Bilimleri Fakültesi",
      "Üniversite Türü": "Devlet",
      "Program Adı": "E",
      "Öğretim Türü": "Örgün",
      "Yıl": [
        "2025",
        "2024",
        "2023",
        "2022",
        "2021"
      ],
      "Kontenjan": [
        "40+1+0+1+060+2+0+2+050+2+0+2+050+250+2"
      ],
      "Yerleşen": [
        "64",
        "62+0+0+2+0",
        "525252"
      ],
      "Taban Sıralama": [
        "236,515",
        "258,170",
        "285,499",
        "338,007"
      ],
      "Taban Puan": [
        "319.736",
        "326.152",
        "322.033",
        "256.758"
      ],
      "Şehir": "Kayseri",
      "Ücret": "Ücretsiz"
    },
    {
      "Program Kodu": "203910266",
      "Üniversite": "Koç Üniversitesi",
      "Fakülte": "İktisadi Ve İdari Bilimler Fakültesi",
      "Üniversite Türü": "Vakıf",
      "Program Adı": "E",
      "Öğretim Türü": "Örgün",
      "Yıl": [
        "2025",
        "2024",
        "2023",
        "2022",
        "2021"
      ],
      "Kontenjan": [
        "80+0+0+0+0105+0+0+0+0112+0+0+0+0109+089+0"
      ],
      "Yerleşen": [
        "105",
        "105+0+0+0+0",
        "11210989"
      ],
      "Taban Sıralama": [
        "240,579",
        "248,006",
        "201,163",
        "211,237"
      ],
      "Taban Puan": [
        "318.901",
        "328.253",
        "342.508",
        "282.52"
      ],
      "Şehir": "İstanbul",
      "Ücret": "Ücretli"
    },
    {
      "Program Kodu": "205090133",
      "Üniversite": "İstanbul Topkapı Üniversitesi",
      "Fakülte": "İktisadi, İdari Ve Sosyal Bilimler Fakültesi",
      "Üniversite Türü": "Vakıf",
      "Program Adı": "E",
      "Öğretim Türü": "Örgün",
      "Yıl": [
        "2025",
        "2024",
        "2023",
        "2022",
        "2021"
      ],
      "Kontenjan": [
        "5+0+1+0+15+0+1+0+14+0+1+0+13+06+0"
      ],
      "Yerleşen": [
        "5",
        "5+0+0+0+0",
        "436"
      ],
      "Taban Sıralama": [
        "244,039",
        "270,388",
        "298,140",
        "408,510"
      ],
      "Taban Puan": [
        "318.191",
        "323.691",
        "319.462",
        "246.014"
      ],
      "Şehir": "İstanbul",
      "Ücret": "Burslu"
    },
    {
      "Program Kodu": "208750663",
      "Üniversite": "İstanbul Kent Üniversitesi",
      "Fakülte": "İktisadi, İdari Ve Sosyal Bilimler Fakültesi",
      "Üniversite Türü": "Vakıf",
      "Program Adı": "E",
      "Öğretim Türü": "Örgün",
      "Yıl": [
        "2025",
        "2024",
        "2023",
        "2022",
        "2021"
      ],
      "Kontenjan": [
        "3+0+0+0+14+0+1+0+1---"
      ],
      "Yerleşen": [
        "5",
        "4+0+0+0+1"
      ],
      "Taban Sıralama": [
        "252,163"
      ],
      "Taban Puan": [
        "316.55"
      ],
      "Şehir": "İstanbul",
      "Ücret": "Burslu"
    },
    {
      "Program Kodu": "202710623",
      "Üniversite": "İstanbul Gelişim Üniversitesi",
      "Fakülte": "İktisadi, İdari Ve Sosyal Bilimler Fakültesi",
      "Üniversite Türü": "Vakıf",
      "Program Adı": "E",
      "Öğretim Türü": "Örgün",
      "Yıl": [
        "2025",
        "2024",
        "2023",
        "2022",
        "2021"
      ],
      "Kontenjan": [
        "6+0+1+0+15+0+1+0+15+0+1+0+18+015+0"
      ],
      "Yerleşen": [
        "5",
        "5+0+0+0+0",
        "6815"
      ],
      "Taban Sıralama": [
        "261,358",
        "274,613",
        "320,929",
        "380,428"
      ],
      "Taban Puan": [
        "314.793",
        "322.854",
        "315.004",
        "250.106"
      ],
      "Şehir": "İstanbul",
      "Ücret": "Burslu"
    },
    {
      "Program Kodu": "210402726",
      "Üniversite": "İstanbul Nişantaşı Üniversitesi",
      "Fakülte": "İktisadi, İdari Ve Sosyal Bilimler Fakültesi",
      "Üniversite Türü": "Vakıf",
      "Program Adı": "E",
      "Öğretim Türü": "Örgün",
      "Yıl": [
        "2025",
        "2024",
        "2023",
        "2022",
        "2021"
      ],
      "Kontenjan": [
        "7+0+1+0+14+0+1+0+1---"
      ],
      "Yerleşen": [
        "5",
        "4+0+0+0+1"
      ],
      "Taban Sıralama": [
        "263,806"
      ],
      "Taban Puan": [
        "314.333"
      ],
      "Şehir": "İstanbul",
      "Ücret": "Burslu"
    },
    {
      "Program Kodu": "205090131",
      "Üniversite": "İstanbul Topkapı Üniversitesi",
      "Fakülte": "İktisadi, İdari Ve Sosyal Bilimler Fakültesi",
      "Üniversite Türü": "Vakıf",
      "Program Adı": "E",
      "Öğretim Türü": "Örgün",
      "Yıl": [
        "2025",
        "2024",
        "2023",
        "2022",
        "2021"
      ],
      "Kontenjan": [
        "6+0+1+0+17+0+1+0+15+0+1+0+15+09+0"
      ],
      "Yerleşen": [
        "8",
        "7+0+0+0+1",
        "659"
      ],
      "Taban Sıralama": [
        "266,145",
        "279,460",
        "347,049",
        "540,009"
      ],
      "Taban Puan": [
        "313.886",
        "321.931",
        "0.233",
        "228.568"
      ],
      "Şehir": "İstanbul",
      "Ücret": "Burslu"
    },
    {
      "Program Kodu": "210402705",
      "Üniversite": "İstanbul Nişantaşı Üniversitesi",
      "Fakülte": "İktisadi, İdari Ve Sosyal Bilimler Fakültesi",
      "Üniversite Türü": "Vakıf",
      "Program Adı": "E",
      "Öğretim Türü": "Örgün",
      "Yıl": [
        "2025",
        "2024",
        "2023",
        "2022",
        "2021"
      ],
      "Kontenjan": [
        "7+0+1+0+14+0+1+0+1---"
      ],
      "Yerleşen": [
        "5",
        "4+0+0+0+1"
      ],
      "Taban Sıralama": [
        "276,527"
      ],
      "Taban Puan": [
        "311.971"
      ],
      "Şehir": "İstanbul",
      "Ücret": "Burslu"
    },
    {
      "Program Kodu": "111710421",
      "Üniversite": "Ankara Hacı Bayram Veli Üniversitesi",
      "Fakülte": "İktisadi Ve İdari Bilimler Fakültesi",
      "Üniversite Türü": "Devlet",
      "Program Adı": "Ç",
      "Öğretim Türü": "Örgün",
      "Yıl": [
        "2025",
        "2024",
        "2023",
        "2022",
        "2021"
      ],
      "Kontenjan": [
        "45+2+0+2+095+3+0+3+090+3+0+3+090+390+3"
      ],
      "Yerleşen": [
        "101",
        "97+1+0+3+0",
        "959393"
      ],
      "Taban Sıralama": [
        "284,370",
        "343,457",
        "398,568",
        "421,662"
      ],
      "Taban Puan": [
        "310.593",
        "310.456",
        "301.718",
        "244.21"
      ],
      "Şehir": "Ankara",
      "Ücret": "Ücretsiz"
    },
    {
      "Program Kodu": "210000479",
      "Üniversite": "Mudanya Üniversitesi",
      "Fakülte": "Sanat Ve Sosyal Bilimler Fakültesi",
      "Üniversite Türü": "Vakıf",
      "Program Adı": "E",
      "Öğretim Türü": "Örgün",
      "Yıl": [
        "2025",
        "2024",
        "2023",
        "2022",
        "2021"
      ],
      "Kontenjan": [
        "4+0+1+0+14+0+1+0+1---"
      ],
      "Yerleşen": [
        "5",
        "4+0+0+0+1"
      ],
      "Taban Sıralama": [
        "289,828"
      ],
      "Taban Puan": [
        "309.653"
      ],
      "Şehir": "Bursa",
      "Ücret": "Burslu"
    },
    {
      "Program Kodu": "206090379",
      "Üniversite": "Yaşar Üniversitesi",
      "Fakülte": "Tarım Bilimleri Ve Teknolojileri Fakültesi",
      "Üniversite Türü": "Vakıf",
      "Program Adı": "T",
      "Öğretim Türü": "Örgün",
      "Yıl": [
        "2025",
        "2024",
        "2023",
        "2022",
        "2021"
      ],
      "Kontenjan": [
        "5+0+1+0+15+0+1+0+14+0+1+0+19+015+0"
      ],
      "Yerleşen": [
        "6",
        "5+0+1+0+0",
        "5915"
      ],
      "Taban Sıralama": [
        "291,778",
        "202,702",
        "331,954",
        "576,775"
      ],
      "Taban Puan": [
        "309.324",
        "338.695",
        "312.929",
        "216.627"
      ],
      "Şehir": "İzmir",
      "Ücret": "Burslu"
    },
    {
      "Program Kodu": "101110942",
      "Üniversite": "Ankara Üniversitesi",
      "Fakülte": "Ziraat Fakültesi",
      "Üniversite Türü": "Devlet",
      "Program Adı": "T",
      "Öğretim Türü": "Örgün",
      "Yıl": [
        "2025",
        "2024",
        "2023",
        "2022",
        "2021"
      ],
      "Kontenjan": [
        "45+2+0+0+045+2+0+0+050+2+0+2+050+250+2"
      ],
      "Yerleşen": [
        "47",
        "47+0+0+0+0",
        "545252"
      ],
      "Taban Sıralama": [
        "310,173",
        "330,604",
        "329,627",
        "337,459"
      ],
      "Taban Puan": [
        "306.242",
        "312.628",
        "313.362",
        "256.844"
      ],
      "Şehir": "Ankara",
      "Ücret": "Ücretsiz"
    },
    {
      "Program Kodu": "206190354",
      "Üniversite": "Yeditepe Üniversitesi",
      "Fakülte": "İktisadi Ve İdari Bilimler Fakültesi",
      "Üniversite Türü": "Vakıf",
      "Program Adı": "E",
      "Öğretim Türü": "Örgün",
      "Yıl": [
        "2025",
        "2024",
        "2023",
        "2022",
        "2021"
      ],
      "Kontenjan": [
        "38+0+0+0+038+0+0+0+032+0+0+0+032+032+0"
      ],
      "Yerleşen": [
        "38",
        "38+0+0+0+0",
        "323232"
      ],
      "Taban Sıralama": [
        "320,904",
        "359,867",
        "338,693",
        "407,529"
      ],
      "Taban Puan": [
        "304.463",
        "307.828",
        "311.702",
        "246.153"
      ],
      "Şehir": "İstanbul",
      "Ücret": "%50 İndirimli"
    },
    {
      "Program Kodu": "103410669",
      "Üniversite": "Ege Üniversitesi",
      "Fakülte": "Ziraat Fakültesi",
      "Üniversite Türü": "Devlet",
      "Program Adı": "T",
      "Öğretim Türü": "Örgün",
      "Yıl": [
        "2025",
        "2024",
        "2023",
        "2022",
        "2021"
      ],
      "Kontenjan": [
        "40+1+0+0+040+1+0+0+040+1+0+1+040+140+1"
      ],
      "Yerleşen": [
        "41",
        "41+0+0+0+0",
        "424141"
      ],
      "Taban Sıralama": [
        "349,735",
        "369,890",
        "362,721",
        "344,213"
      ],
      "Taban Puan": [
        "299.988",
        "306.278",
        "307.535",
        "255.734"
      ],
      "Şehir": "İzmir",
      "Ücret": "Ücretsiz"
    },
    {
      "Program Kodu": "100710506",
      "Üniversite": "Akdeniz Üniversitesi",
      "Fakülte": "Ziraat Fakültesi",
      "Üniversite Türü": "Devlet",
      "Program Adı": "T",
      "Öğretim Türü": "Örgün",
      "Yıl": [
        "2025",
        "2024",
        "2023",
        "2022",
        "2021"
      ],
      "Kontenjan": [
        "30+1+0+1+030+1+0+1+040+1+0+1+040+140+1"
      ],
      "Yerleşen": [
        "32",
        "30+1+0+1+0",
        "424141"
      ],
      "Taban Sıralama": [
        "352,969",
        "425,108",
        "382,792",
        "368,303"
      ],
      "Taban Puan": [
        "299.501",
        "298.233",
        "304.219",
        "251.945"
      ],
      "Şehir": "Antalya",
      "Ücret": "Ücretsiz"
    },
    {
      "Program Kodu": "103110318",
      "Üniversite": "Dokuz Eylül Üniversitesi",
      "Fakülte": "İktisadi Ve İdari Bilimler Fakültesi",
      "Üniversite Türü": "Devlet",
      "Program Adı": "Ç",
      "Öğretim Türü": "Örgün",
      "Yıl": [
        "2025",
        "2024",
        "2023",
        "2022",
        "2021"
      ],
      "Kontenjan": [
        "45+2+0+0+0110+3+0+0+0100+3+0+3+0100+3100+3"
      ],
      "Yerleşen": [
        "113",
        "112+1+0+0+0",
        "103103103"
      ],
      "Taban Sıralama": [
        "354,189",
        "426,110",
        "416,404",
        "435,206"
      ],
      "Taban Puan": [
        "299.323",
        "298.093",
        "299.038",
        "242.392"
      ],
      "Şehir": "İzmir",
      "Ücret": "Ücretsiz"
    },
    {
      "Program Kodu": "200511065",
      "Üniversite": "Bahçeşehir Üniversitesi",
      "Fakülte": "İktisadi, İdari Ve Sosyal Bilimler Fakültesi",
      "Üniversite Türü": "Vakıf",
      "Program Adı": "E",
      "Öğretim Türü": "Örgün",
      "Yıl": [
        "2025",
        "2024",
        "2023",
        "2022",
        "2021"
      ],
      "Kontenjan": [
        "36+0+0+0+022+0+0+0+022+0+0+0+022+021+0"
      ],
      "Yerleşen": [
        "22",
        "22+0+0+0+0",
        "222221"
      ],
      "Taban Sıralama": [
        "355,945",
        "340,999",
        "289,445",
        "307,656"
      ],
      "Taban Puan": [
        "299.068",
        "310.864",
        "321.202",
        "261.988"
      ],
      "Şehir": "İstanbul",
      "Ücret": "%50 İndirimli"
    },
    {
      "Program Kodu": "207590380",
      "Üniversite": "İstanbul Esenyurt Üniversitesi",
      "Fakülte": "İşletme Ve Yönetim Bilimleri Fakültesi",
      "Üniversite Türü": "Vakıf",
      "Program Adı": "E",
      "Öğretim Türü": "Örgün",
      "Yıl": [
        "2025",
        "2024",
        "2023",
        "2022",
        "2021"
      ],
      "Kontenjan": [
        "6+0+0+0+14+0+1+0+15+0+1+0+1--"
      ],
      "Yerleşen": [
        "6",
        "4+0+1+0+1",
        "6"
      ],
      "Taban Sıralama": [
        "369,776",
        "405,404"
      ],
      "Taban Puan": [
        "297.075",
        "301.022"
      ],
      "Şehir": "İstanbul",
      "Ücret": "Burslu"
    },
    {
      "Program Kodu": "101010264",
      "Üniversite": "Anadolu Üniversitesi",
      "Fakülte": "İktisadi Ve İdari Bilimler Fakültesi",
      "Üniversite Türü": "Devlet",
      "Program Adı": "Ç",
      "Öğretim Türü": "Örgün",
      "Yıl": [
        "2025",
        "2024",
        "2023",
        "2022",
        "2021"
      ],
      "Kontenjan": [
        "40+1+0+1+095+3+0+3+085+3+0+3+085+385+3"
      ],
      "Yerleşen": [
        "101",
        "98+0+0+3+0",
        "918888"
      ],
      "Taban Sıralama": [
        "373,636",
        "435,949",
        "436,186",
        "473,065"
      ],
      "Taban Puan": [
        "296.523",
        "296.742",
        "96.129",
        "237.552"
      ],
      "Şehir": "Eskişehir",
      "Ücret": "Ücretsiz"
    }
  ]
}