{
  "yks": [
    {
      "Program Kodu": "200690762",
      "Üniversite": "Başkent Üniversitesi",
      "Fakülte": "Sosyal Bilimler Meslek Yüksekokulu",
      "Üniversite Türü": "Vakıf",
      "Program Adı": "P",
      "Öğretim Türü": "Örgün",
      "Yıl": [
        "2025",
        "2024",
        "2023",
        "2022",
        "2021"
      ],
      "Kontenjan": [
        "6+0+0+0+14+0+0+0+15+0+0+0+1--"
      ],
      "Yerleşen": [
        "4+0+0+0+1",
        "Doldu-6"
      ],
      "Taban Sıralama": [
        "366,917",
        "280,857"
      ],
      "Taban Puan": [
        "357.617",
        "376.59"
      ],
      "Şehir": "Ankara",
      "Ücret": "Burslu"
    },
    {
      "Program Kodu": "208151176",
      "Üniversite": "İstanbul Rumeli Üniversitesi",
      "Fakülte": "Meslek Yüksekokulu",
      "Üniversite Türü": "Vakıf",
      "Program Adı": "P",
      "Öğretim Türü": "Örgün",
      "Yıl": [
        "2025",
        "2024",
        "2023",
        "2022",
        "2021"
      ],
      "Kontenjan": [
        "2+0+0+0+12+0+0+0+14+0+0+0+1--"
      ],
      "Yerleşen": [
        "2+0+0+0+1",
        "Doldu-5"
      ],
      "Taban Sıralama": [
        "391,195",
        "760,942"
      ],
      "Taban Puan": [
        "353.414",
        "310.719"
      ],
      "Şehir": "İstanbul",
      "Ücret": "Burslu"
    },
    {
      "Program Kodu": "202790613",
      "Üniversite": "İstanbul Gelişim Üniversitesi",
      "Fakülte": "İstanbul Gelişim Meslek Yüksekokulu",
      "Üniversite Türü": "Vakıf",
      "Program Adı": "P",
      "Öğretim Türü": "Örgün",
      "Yıl": [
        "2025",
        "2024",
        "2023",
        "2022",
        "2021"
      ],
      "Kontenjan": [
        "5+0+1+0+15+0+1+0+16+0+1+0+1--"
      ],
      "Yerleşen": [
        "5+0+0+0+1",
        "7"
      ],
      "Taban Sıralama": [
        "682,033"
      ],
      "Taban Puan": [
        "317.302"
      ],
      "Şehir": "İstanbul",
      "Ücret": "Burslu"
    },
    {
      "Program Kodu": "100790467",
      "Üniversite": "Akdeniz Üniversitesi",
      "Fakülte": "Göynük Mutfak Sanatları Meslek Yüksekokulu",
      "Üniversite Türü": "Devlet",
      "Program Adı": "P",
      "Öğretim Türü": "Örgün",
      "Yıl": [
        "2025",
        "2024",
        "2023",
        "2022",
        "2021"
      ],
      "Kontenjan": [
        "30+1+0+1+030+1+0+1+030+1+0+1+0--"
      ],
      "Yerleşen": [
        "30+1+0+1+0",
        "Doldu-32"
      ],
      "Taban Sıralama": [
        "818,310",
        "872,118"
      ],
      "Taban Puan": [
        "305.175",
        "300.881"
      ],
      "Şehir": "Antalya",
      "Ücret": "Ücretsiz"
    },
    {
      "Program Kodu": "111890231",
      "Üniversite": "Sakarya Uygulamalı Bilimler Üniversitesi",
      "Fakülte": "Sapanca Turizm Meslek Yüksekokulu",
      "Üniversite Türü": "Devlet",
      "Program Adı": "P",
      "Öğretim Türü": "Örgün",
      "Yıl": [
        "2025",
        "2024",
        "2023",
        "2022",
        "2021"
      ],
      "Kontenjan": [
        "30+1+0+1+030+1+0+1+030+1+0+1+0--"
      ],
      "Yerleşen": [
        "31+0+0+1+0",
        "Doldu-32"
      ],
      "Taban Sıralama": [
        "914,462",
        "983,771"
      ],
      "Taban Puan": [
        "297.554",
        "291.856"
      ],
      "Şehir": "Sakarya",
      "Ücret": "Ücretsiz"
    },
    {
      "Program Kodu": "100190250",
      "Üniversite": "Bolu Abant İzzet Baysal Üniversitesi",
      "Fakülte": "Mengen Meslek Yüksekokulu",
      "Üniversite Türü": "Devlet",
      "Program Adı": "P",
      "Öğretim Türü": "Örgün",
      "Yıl": [
        "2025",
        "2024",
        "2023",
        "2022",
        "2021"
      ],
      "Kontenjan": [
        "30+1+0+1+030+1+0+1+0---"
      ],
      "Yerleşen": [
        "30+1+0+1+0"
      ],
      "Taban Sıralama": [
        "1,159"
      ],
      "Taban Puan": [
        "280.235"
      ],
      "Şehir": "Bolu",
      "Ücret": "Ücretsiz"
    },
    {
      "Program Kodu": "300190382",
      "Üniversite": "Doğu Akdeniz ÜniversitesiKKTCTurizm Ve Otelcilik Yüksekokulu",
      "Fakülte": "",
      "Üniversite Türü": "",
      "Program Adı": "P",
      "Öğretim Türü": "Örgün",
      "Yıl": [
        "2025",
        "2024",
        "2023",
        "2022",
        "2021"
      ],
      "Kontenjan": [
        "5+0+0+0+05+0+0+0+07+0+0+0+0--"
      ],
      "Yerleşen": [
        "5+0+0+0+0",
        "Doldu-7"
      ],
      "Taban Sıralama": [
        "1,282",
        "471,809"
      ],
      "Taban Puan": [
        "272.285",
        "239.033"
      ],
      "Şehir": "Famagusta",
      "Ücret": "Burslu"
    },
    {
      "Program Kodu": "106390067",
      "Üniversite": "Karamanoğlu Mehmetbey Üniversitesi",
      "Fakülte": "Sosyal Bilimler Meslek Yüksekokulu",
      "Üniversite Türü": "Devlet",
      "Program Adı": "P",
      "Öğretim Türü": "Örgün",
      "Yıl": [
        "2025",
        "2024",
        "2023",
        "2022",
        "2021"
      ],
      "Kontenjan": [
        "30+1+0+1+030+1+0+1+030+1+0+1+0--"
      ],
      "Yerleşen": [
        "31+0+0+1+0",
        "Doldu-32"
      ],
      "Taban Sıralama": [
        "1,324",
        "051,341"
      ],
      "Taban Puan": [
        "269.628",
        "266.682"
      ],
      "Şehir": "Karaman",
      "Ücret": "Ücretsiz"
    },
    {
      "Program Kodu": "101790198",
      "Üniversite": "Batman Üniversitesi",
      "Fakülte": "Hasankeyf Meslek Yüksekokulu",
      "Üniversite Türü": "Devlet",
      "Program Adı": "P",
      "Öğretim Türü": "Örgün",
      "Yıl": [
        "2025",
        "2024",
        "2023",
        "2022",
        "2021"
      ],
      "Kontenjan": [
        "30+1+0+1+030+1+0+1+0---"
      ],
      "Yerleşen": [
        "31+0+0+1+0"
      ],
      "Taban Sıralama": [
        "1,700"
      ],
      "Taban Puan": [
        "247.25"
      ],
      "Şehir": "Batman",
      "Ücret": "Ücretsiz"
    },
    {
      "Program Kodu": "300390362",
      "Üniversite": "Lefke Avrupa ÜniversitesiKKTCMeslek Yüksekokulu",
      "Fakülte": "",
      "Üniversite Türü": "",
      "Program Adı": "P",
      "Öğretim Türü": "Örgün",
      "Yıl": [
        "2025",
        "2024",
        "2023",
        "2022",
        "2021"
      ],
      "Kontenjan": [
        "7+0+0+0+07+0+0+0+07+0+0+0+0--"
      ],
      "Yerleşen": [
        "7+0+0+0+0",
        "Doldu-7"
      ],
      "Taban Sıralama": [
        "1,817",
        "222,054"
      ],
      "Taban Puan": [
        "240.647",
        "226.047"
      ],
      "Şehir": "Karavostasi",
      "Ücret": "Burslu"
    },
    {
      "Program Kodu": "200690769",
      "Üniversite": "Başkent Üniversitesi",
      "Fakülte": "Sosyal Bilimler Meslek Yüksekokulu",
      "Üniversite Türü": "Vakıf",
      "Program Adı": "P",
      "Öğretim Türü": "Örgün",
      "Yıl": [
        "2025",
        "2024",
        "2023",
        "2022",
        "2021"
      ],
      "Kontenjan": [
        "17+0+0+0+019+0+0+0+020+0+0+0+0--"
      ],
      "Yerleşen": [
        "19+0+0+0+0",
        "Doldu-20"
      ],
      "Taban Sıralama": [
        "2,330",
        "672,779"
      ],
      "Taban Puan": [
        "212.625",
        "187.145"
      ],
      "Şehir": "Ankara",
      "Ücret": "%25 İndirimli"
    },
    {
      "Program Kodu": "208151183",
      "Üniversite": "İstanbul Rumeli Üniversitesi",
      "Fakülte": "Meslek Yüksekokulu",
      "Üniversite Türü": "Vakıf",
      "Program Adı": "P",
      "Öğretim Türü": "Örgün",
      "Yıl": [
        "2025",
        "2024",
        "2023",
        "2022",
        "2021"
      ],
      "Kontenjan": [
        "13+0+0+0+013+0+0+0+021+0+0+0+0--"
      ],
      "Yerleşen": [
        "13+0+0+0+0",
        "Doldu-21"
      ],
      "Taban Sıralama": [
        "2,361",
        "942,435"
      ],
      "Taban Puan": [
        "210.912",
        "207.185"
      ],
      "Şehir": "İstanbul",
      "Ücret": "%50 İndirimli"
    },
    {
      "Program Kodu": "202790620",
      "Üniversite": "İstanbul Gelişim Üniversitesi",
      "Fakülte": "İstanbul Gelişim Meslek Yüksekokulu",
      "Üniversite Türü": "Vakıf",
      "Program Adı": "P",
      "Öğretim Türü": "Örgün",
      "Yıl": [
        "2025",
        "2024",
        "2023",
        "2022",
        "2021"
      ],
      "Kontenjan": [
        "37+0+0+0+037+0+0+0+038+0+0+0+0--"
      ],
      "Yerleşen": [
        "37+0+0+0+0",
        "Doldu-38"
      ],
      "Taban Sıralama": [
        "2,721",
        "922,262"
      ],
      "Taban Puan": [
        "181.545",
        "215.661"
      ],
      "Şehir": "İstanbul",
      "Ücret": "%50 İndirimli"
    },
    {
      "Program Kodu": "300190381",
      "Üniversite": "Doğu Akdeniz ÜniversitesiKKTCTurizm Ve Otelcilik Yüksekokulu",
      "Fakülte": "",
      "Üniversite Türü": "",
      "Program Adı": "P",
      "Öğretim Türü": "Örgün",
      "Yıl": [
        "2025",
        "2024",
        "2023",
        "2022",
        "2021"
      ],
      "Kontenjan": [
        "12+0+0+0+012+0+0+0+010+0+0+0+0--"
      ],
      "Yerleşen": [
        "7+0+0+0+0",
        "Doldu-5"
      ],
      "Taban Sıralama": [],
      "Taban Puan": [],
      "Şehir": "Famagusta",
      "Ücret": "Ücretli"
    },
    {
      "Program Kodu": "106390136",
      "Üniversite": "Karamanoğlu Mehmetbey Üniversitesi",
      "Fakülte": "Sosyal Bilimler Meslek Yüksekokulu",
      "Üniversite Türü": "Devlet",
      "Program Adı": "P",
      "Öğretim Türü": "Örgün",
      "Yıl": [
        "2025",
        "2024",
        "2023",
        "2022",
        "2021"
      ],
      "Kontenjan": [
        "1+0+0+0+01+0+0+0+0---"
      ],
      "Yerleşen": [
        "0+0+0+0"
      ],
      "Taban Sıralama": [],
      "Taban Puan": [],
      "Şehir": "Karaman",
      "Ücret": "Ücretsiz"
    },
    {
      "Program Kodu": "300390369",
      "Üniversite": "Lefke Avrupa ÜniversitesiKKTCMeslek Yüksekokulu",
      "Fakülte": "",
      "Üniversite Türü": "",
      "Program Adı": "P",
      "Öğretim Türü": "Örgün",
      "Yıl": [
        "2025",
        "2024",
        "2023",
        "2022",
        "2021"
      ],
      "Kontenjan": [
        "8+0+0+0+08+0+0+0+08+0+0+0+0--"
      ],
      "Yerleşen": [
        "5+0+0+0+0",
        "Doldu-8"
      ],
      "Taban Sıralama": [
        "2,716"
      ],
      "Taban Puan": [
        "191.874"
      ],
      "Şehir": "Karavostasi",
      "Ücret": "%50 İndirimli"
    },
    {
      "Program Kodu": "101890315",
      "Üniversite": "Bayburt Üniversitesi",
      "Fakülte": "Sosyal Bilimler Meslek Yüksekokulu",
      "Üniversite Türü": "Devlet",
      "Program Adı": "P",
      "Öğretim Türü": "Örgün",
      "Yıl": [
        "2025",
        "2024",
        "2023",
        "2022",
        "2021"
      ],
      "Kontenjan": [
        "30+1+0+1+0----"
      ],
      "Yerleşen": [],
      "Taban Sıralama": [],
      "Taban Puan": [],
      "Şehir": "Bayburt",
      "Ücret": "Ücretsiz"
    }
  ]
}